[{"id":35,"phaseName":"Production and Industrial Engineering","phaseUniqueName":"GATE PI","exam":{"id":21,"nameShort":"GATE PI","examName":"Graduate Aptitude Test in Engineering for Production and Industrial Engineering ","description":"Graduate Aptitude Test in Engineering (GATE) is a national examination conducted jointly by the Indian Institute of Science (IISc) Bangalore and seven Indian Institutes of Technology (IITs) at Bombay, Delhi, Guwahati, Kanpur, Kharagpur, Madras, and Roorkee on behalf of National Coordination Board (NCB)-GATE, Department of Higher Education, Ministry of Education (MoE), Government of India. GATE examination is a Computer Based Test (CBT).","patterDetails":null,"published_at":"2021-11-10T13:25:38.000Z","created_at":"2021-11-10T05:59:48.000Z","updated_at":"2021-11-11T14:42:30.000Z"},"published_at":"2021-11-10T06:03:31.000Z","created_at":"2021-11-10T06:00:58.000Z","updated_at":"2021-11-11T14:43:39.000Z","phaseDescription":null,"subjects":[{"id":13,"subjectUniqueName":null,"subjectWeightage":null,"subjectName":"Engineering Mathematics","published_at":"2021-08-27T14:53:29.000Z","created_at":"2021-08-27T14:53:21.000Z","updated_at":"2021-11-10T06:02:02.000Z","subjectDescription":""},{"id":98,"subjectUniqueName":null,"subjectWeightage":null,"subjectName":"General Engineering","published_at":"2021-11-10T06:04:06.000Z","created_at":"2021-11-10T06:04:04.000Z","updated_at":"2021-11-10T06:04:06.000Z","subjectDescription":null},{"id":99,"subjectUniqueName":null,"subjectWeightage":null,"subjectName":"Manufacturing Processes I","published_at":"2021-11-10T06:05:35.000Z","created_at":"2021-11-10T06:05:33.000Z","updated_at":"2021-11-10T06:05:35.000Z","subjectDescription":null},{"id":100,"subjectUniqueName":null,"subjectWeightage":null,"subjectName":"Manufacturing Processes II","published_at":"2021-11-10T06:06:31.000Z","created_at":"2021-11-10T06:06:29.000Z","updated_at":"2021-11-10T06:06:31.000Z","subjectDescription":null},{"id":101,"subjectUniqueName":null,"subjectWeightage":null,"subjectName":"Quality and Reliability","published_at":"2021-11-10T06:07:43.000Z","created_at":"2021-11-10T06:07:40.000Z","updated_at":"2021-11-10T06:07:43.000Z","subjectDescription":null},{"id":102,"subjectUniqueName":null,"subjectWeightage":null,"subjectName":"Industrial Engineering","published_at":"2021-11-10T06:08:34.000Z","created_at":"2021-11-10T06:08:30.000Z","updated_at":"2021-11-10T06:08:34.000Z","subjectDescription":null},{"id":103,"subjectUniqueName":null,"subjectWeightage":null,"subjectName":"Operations research and Operations management","published_at":"2021-11-10T06:09:28.000Z","created_at":"2021-11-10T06:09:26.000Z","updated_at":"2021-11-10T06:09:28.000Z","subjectDescription":null},{"id":17,"subjectUniqueName":null,"subjectWeightage":null,"subjectName":"General Aptitude","published_at":"2021-08-28T07:35:15.000Z","created_at":"2021-08-28T07:35:12.000Z","updated_at":"2021-11-10T06:10:42.000Z","subjectDescription":null}],"chapters":[{"id":197,"chapterName":"Verbal Aptitude","chapterUniqueName":null,"subject":17,"published_at":"2021-08-28T07:37:40.000Z","created_at":"2021-08-28T07:37:38.000Z","updated_at":"2021-11-10T06:22:23.000Z","chapterDetails":null},{"id":198,"chapterName":"Quantitative Aptitude","chapterUniqueName":null,"subject":17,"published_at":"2021-08-28T07:44:27.000Z","created_at":"2021-08-28T07:44:25.000Z","updated_at":"2021-11-10T06:25:31.000Z","chapterDetails":null},{"id":199,"chapterName":"Analytical Aptitude","chapterUniqueName":null,"subject":17,"published_at":"2021-08-28T07:51:31.000Z","created_at":"2021-08-28T07:51:29.000Z","updated_at":"2021-11-10T06:30:54.000Z","chapterDetails":null},{"id":200,"chapterName":"Spatial Aptitude","chapterUniqueName":null,"subject":17,"published_at":"2021-08-28T07:51:57.000Z","created_at":"2021-08-28T07:51:55.000Z","updated_at":"2021-11-10T06:32:15.000Z","chapterDetails":null},{"id":174,"chapterName":"Linear Algebra","chapterUniqueName":null,"subject":13,"published_at":"2021-08-27T15:08:17.000Z","created_at":"2021-08-27T15:08:15.000Z","updated_at":"2021-11-10T06:35:02.000Z","chapterDetails":null},{"id":175,"chapterName":"Calculus","chapterUniqueName":null,"subject":13,"published_at":"2021-08-27T15:21:11.000Z","created_at":"2021-08-27T15:21:09.000Z","updated_at":"2021-11-10T06:36:29.000Z","chapterDetails":null},{"id":176,"chapterName":"Differential equations","chapterUniqueName":null,"subject":13,"published_at":"2021-08-27T15:36:30.000Z","created_at":"2021-08-27T15:36:25.000Z","updated_at":"2021-11-10T07:08:46.000Z","chapterDetails":null},{"id":177,"chapterName":"Complex variables","chapterUniqueName":null,"subject":13,"published_at":"2021-08-27T15:44:08.000Z","created_at":"2021-08-27T15:44:05.000Z","updated_at":"2021-11-10T07:10:34.000Z","chapterDetails":null},{"id":178,"chapterName":"Probability and Statistics","chapterUniqueName":null,"subject":13,"published_at":"2021-08-27T15:51:29.000Z","created_at":"2021-08-27T15:51:27.000Z","updated_at":"2021-11-10T07:11:48.000Z","chapterDetails":null},{"id":179,"chapterName":"Numerical Methods","chapterUniqueName":null,"subject":13,"published_at":"2021-08-27T16:01:37.000Z","created_at":"2021-08-27T16:01:35.000Z","updated_at":"2021-11-10T07:15:45.000Z","chapterDetails":null},{"id":591,"chapterName":"Engineering Materials","chapterUniqueName":null,"subject":98,"published_at":"2021-11-10T07:18:33.000Z","created_at":"2021-11-10T07:18:30.000Z","updated_at":"2021-11-10T07:18:33.000Z","chapterDetails":null},{"id":592,"chapterName":"Applied Mechanics","chapterUniqueName":null,"subject":98,"published_at":"2021-11-10T07:21:21.000Z","created_at":"2021-11-10T07:21:18.000Z","updated_at":"2021-11-10T07:21:21.000Z","chapterDetails":null},{"id":593,"chapterName":"Theory of Machines and Design","chapterUniqueName":null,"subject":98,"published_at":"2021-11-10T07:23:51.000Z","created_at":"2021-11-10T07:23:48.000Z","updated_at":"2021-11-10T07:23:51.000Z","chapterDetails":null},{"id":594,"chapterName":"Thermal and Fluids Engineering","chapterUniqueName":null,"subject":98,"published_at":"2021-11-10T07:26:46.000Z","created_at":"2021-11-10T07:26:08.000Z","updated_at":"2021-11-10T07:26:46.000Z","chapterDetails":null},{"id":595,"chapterName":"Casting","chapterUniqueName":null,"subject":99,"published_at":"2021-11-10T07:30:09.000Z","created_at":"2021-11-10T07:30:07.000Z","updated_at":"2021-11-10T07:30:09.000Z","chapterDetails":null},{"id":596,"chapterName":"Metal Forming","chapterUniqueName":null,"subject":99,"published_at":"2021-11-10T07:33:24.000Z","created_at":"2021-11-10T07:33:13.000Z","updated_at":"2021-11-10T07:33:24.000Z","chapterDetails":null},{"id":597,"chapterName":"Joining of Materials","chapterUniqueName":null,"subject":99,"published_at":"2021-11-10T07:36:01.000Z","created_at":"2021-11-10T07:35:57.000Z","updated_at":"2021-11-10T07:36:01.000Z","chapterDetails":null},{"id":598,"chapterName":"Powder Processing","chapterUniqueName":null,"subject":99,"published_at":"2021-11-10T07:38:14.000Z","created_at":"2021-11-10T07:38:12.000Z","updated_at":"2021-11-10T07:38:14.000Z","chapterDetails":null},{"id":599,"chapterName":"Polymers and Composites","chapterUniqueName":null,"subject":99,"published_at":"2021-11-10T07:40:13.000Z","created_at":"2021-11-10T07:40:11.000Z","updated_at":"2021-11-10T07:40:13.000Z","chapterDetails":null},{"id":600,"chapterName":"Machining","chapterUniqueName":null,"subject":100,"published_at":"2021-11-10T07:41:51.000Z","created_at":"2021-11-10T07:41:48.000Z","updated_at":"2021-11-10T07:41:51.000Z","chapterDetails":null},{"id":601,"chapterName":"Machine Tools","chapterUniqueName":null,"subject":100,"published_at":"2021-11-10T07:46:24.000Z","created_at":"2021-11-10T07:46:22.000Z","updated_at":"2021-11-10T07:46:24.000Z","chapterDetails":null},{"id":602,"chapterName":"Advanced Manufacturing","chapterUniqueName":null,"subject":100,"published_at":"2021-11-10T07:49:03.000Z","created_at":"2021-11-10T07:49:00.000Z","updated_at":"2021-11-10T07:49:04.000Z","chapterDetails":null},{"id":603,"chapterName":"Computer Integrated Manufacturing","chapterUniqueName":null,"subject":100,"published_at":"2021-11-10T07:50:57.000Z","created_at":"2021-11-10T07:50:48.000Z","updated_at":"2021-11-10T07:50:57.000Z","chapterDetails":null},{"id":604,"chapterName":"Metrology and Inspection","chapterUniqueName":null,"subject":101,"published_at":"2021-11-10T07:52:34.000Z","created_at":"2021-11-10T07:52:32.000Z","updated_at":"2021-11-10T07:52:34.000Z","chapterDetails":null},{"id":605,"chapterName":"Quality Management","chapterUniqueName":null,"subject":101,"published_at":"2021-11-10T07:54:21.000Z","created_at":"2021-11-10T07:54:19.000Z","updated_at":"2021-11-10T07:54:21.000Z","chapterDetails":null},{"id":606,"chapterName":"Reliability and Maintenance","chapterUniqueName":null,"subject":101,"published_at":"2021-11-10T07:56:06.000Z","created_at":"2021-11-10T07:56:04.000Z","updated_at":"2021-11-10T07:56:06.000Z","chapterDetails":null},{"id":607,"chapterName":"Product Design and Development","chapterUniqueName":null,"subject":102,"published_at":"2021-11-10T07:58:04.000Z","created_at":"2021-11-10T07:58:01.000Z","updated_at":"2021-11-10T07:58:05.000Z","chapterDetails":null},{"id":608,"chapterName":"Work System Design","chapterUniqueName":null,"subject":102,"published_at":"2021-11-10T07:59:56.000Z","created_at":"2021-11-10T07:59:52.000Z","updated_at":"2021-11-10T07:59:56.000Z","chapterDetails":null},{"id":609,"chapterName":"Facility Design","chapterUniqueName":null,"subject":102,"published_at":"2021-11-10T08:01:32.000Z","created_at":"2021-11-10T08:01:27.000Z","updated_at":"2021-11-10T08:01:32.000Z","chapterDetails":null},{"id":610,"chapterName":"Operation Research","chapterUniqueName":null,"subject":103,"published_at":"2021-11-10T08:02:49.000Z","created_at":"2021-11-10T08:02:46.000Z","updated_at":"2021-11-10T08:02:49.000Z","chapterDetails":null},{"id":611,"chapterName":"Engineering Economy and Costing","chapterUniqueName":null,"subject":103,"published_at":"2021-11-10T08:04:12.000Z","created_at":"2021-11-10T08:04:09.000Z","updated_at":"2021-11-10T08:04:12.000Z","chapterDetails":null},{"id":612,"chapterName":"Production control","chapterUniqueName":null,"subject":103,"published_at":"2021-11-10T08:05:17.000Z","created_at":"2021-11-10T08:05:15.000Z","updated_at":"2021-11-10T08:05:17.000Z","chapterDetails":null},{"id":613,"chapterName":"Project management","chapterUniqueName":null,"subject":103,"published_at":"2021-11-10T13:17:14.000Z","created_at":"2021-11-10T13:17:12.000Z","updated_at":"2021-11-10T13:17:14.000Z","chapterDetails":null}],"topic_details":[{"id":1675,"topicName":"Basic English grammar","topicDescription":null,"topicUniqueName":null,"chapter":197,"published_at":"2021-08-28T07:38:17.000Z","created_at":"2021-08-28T07:38:15.000Z","updated_at":"2021-11-10T06:22:31.000Z"},{"id":1676,"topicName":"Tenses","topicDescription":null,"topicUniqueName":null,"chapter":197,"published_at":"2021-08-28T07:38:40.000Z","created_at":"2021-08-28T07:38:38.000Z","updated_at":"2021-11-10T06:22:46.000Z"},{"id":1677,"topicName":"Articles","topicDescription":null,"topicUniqueName":null,"chapter":197,"published_at":"2021-08-28T07:39:01.000Z","created_at":"2021-08-28T07:39:00.000Z","updated_at":"2021-11-10T06:22:55.000Z"},{"id":1678,"topicName":"Adjectives","topicDescription":null,"topicUniqueName":null,"chapter":197,"published_at":"2021-08-28T07:39:24.000Z","created_at":"2021-08-28T07:39:22.000Z","updated_at":"2021-11-10T06:23:07.000Z"},{"id":1679,"topicName":"Prepositions","topicDescription":null,"topicUniqueName":null,"chapter":197,"published_at":"2021-08-28T07:39:50.000Z","created_at":"2021-08-28T07:39:48.000Z","updated_at":"2021-11-10T06:23:18.000Z"},{"id":1680,"topicName":"Conjunctions","topicDescription":null,"topicUniqueName":null,"chapter":197,"published_at":"2021-08-28T07:40:12.000Z","created_at":"2021-08-28T07:40:09.000Z","updated_at":"2021-11-10T06:23:31.000Z"},{"id":1681,"topicName":"Verb-noun agreement and other parts of speech","topicDescription":null,"topicUniqueName":null,"chapter":197,"published_at":"2021-08-28T07:40:46.000Z","created_at":"2021-08-28T07:40:44.000Z","updated_at":"2021-11-10T06:23:42.000Z"},{"id":1682,"topicName":"Basic vocabulary","topicDescription":null,"topicUniqueName":null,"chapter":197,"published_at":"2021-08-28T07:41:15.000Z","created_at":"2021-08-28T07:41:13.000Z","updated_at":"2021-11-10T06:23:56.000Z"},{"id":1683,"topicName":"Words","topicDescription":null,"topicUniqueName":null,"chapter":197,"published_at":"2021-08-28T07:41:38.000Z","created_at":"2021-08-28T07:41:35.000Z","updated_at":"2021-11-10T06:24:12.000Z"},{"id":1684,"topicName":"Idioms","topicDescription":null,"topicUniqueName":null,"chapter":197,"published_at":"2021-08-28T07:42:12.000Z","created_at":"2021-08-28T07:42:10.000Z","updated_at":"2021-11-10T06:24:23.000Z"},{"id":1685,"topicName":"Phrases in context","topicDescription":null,"topicUniqueName":null,"chapter":197,"published_at":"2021-08-28T07:42:36.000Z","created_at":"2021-08-28T07:42:34.000Z","updated_at":"2021-11-10T06:24:34.000Z"},{"id":1686,"topicName":"Reading and comprehension","topicDescription":null,"topicUniqueName":null,"chapter":197,"published_at":"2021-08-28T07:43:15.000Z","created_at":"2021-08-28T07:43:12.000Z","updated_at":"2021-11-10T06:24:48.000Z"},{"id":1687,"topicName":"Narrative sequencing","topicDescription":null,"topicUniqueName":null,"chapter":197,"published_at":"2021-08-28T07:43:38.000Z","created_at":"2021-08-28T07:43:36.000Z","updated_at":"2021-11-10T06:25:01.000Z"},{"id":1688,"topicName":"Data interpretation","topicDescription":null,"topicUniqueName":null,"chapter":198,"published_at":"2021-08-28T07:45:02.000Z","created_at":"2021-08-28T07:45:00.000Z","updated_at":"2021-11-10T06:25:42.000Z"},{"id":1689,"topicName":"Data graphs","topicDescription":"bar graphs, pie charts, and other graphs representing data","topicUniqueName":null,"chapter":198,"published_at":"2021-08-28T07:45:41.000Z","created_at":"2021-08-28T07:45:39.000Z","updated_at":"2021-11-10T06:25:54.000Z"},{"id":1690,"topicName":"2- and 3-dimensional plots","topicDescription":null,"topicUniqueName":null,"chapter":198,"published_at":"2021-08-28T07:46:06.000Z","created_at":"2021-08-28T07:46:04.000Z","updated_at":"2021-11-10T06:26:06.000Z"},{"id":1691,"topicName":"Maps","topicDescription":null,"topicUniqueName":null,"chapter":198,"published_at":"2021-08-28T07:46:30.000Z","created_at":"2021-08-28T07:46:28.000Z","updated_at":"2021-11-10T06:26:16.000Z"},{"id":1692,"topicName":"Tables","topicDescription":null,"topicUniqueName":null,"chapter":198,"published_at":"2021-08-28T07:46:53.000Z","created_at":"2021-08-28T07:46:51.000Z","updated_at":"2021-11-10T06:26:28.000Z"},{"id":1693,"topicName":"Numerical computation and estimation","topicDescription":null,"topicUniqueName":null,"chapter":198,"published_at":"2021-08-28T07:47:24.000Z","created_at":"2021-08-28T07:47:22.000Z","updated_at":"2021-11-10T06:27:36.000Z"},{"id":1694,"topicName":"Ratios","topicDescription":null,"topicUniqueName":null,"chapter":198,"published_at":"2021-08-28T07:47:48.000Z","created_at":"2021-08-28T07:47:45.000Z","updated_at":"2021-11-10T06:28:01.000Z"},{"id":1695,"topicName":"Percentages","topicDescription":null,"topicUniqueName":null,"chapter":198,"published_at":"2021-08-28T07:48:24.000Z","created_at":"2021-08-28T07:48:22.000Z","updated_at":"2021-11-10T06:28:13.000Z"},{"id":1696,"topicName":"Powers","topicDescription":null,"topicUniqueName":null,"chapter":198,"published_at":"2021-08-28T07:48:46.000Z","created_at":"2021-08-28T07:48:44.000Z","updated_at":"2021-11-10T06:28:25.000Z"},{"id":1697,"topicName":"Exponents and logarithms","topicDescription":null,"topicUniqueName":null,"chapter":198,"published_at":"2021-08-28T07:49:14.000Z","created_at":"2021-08-28T07:49:11.000Z","updated_at":"2021-11-10T06:28:39.000Z"},{"id":1698,"topicName":"Permutations and combinations","topicDescription":null,"topicUniqueName":null,"chapter":198,"published_at":"2021-08-28T07:49:35.000Z","created_at":"2021-08-28T07:49:33.000Z","updated_at":"2021-11-10T06:28:55.000Z"},{"id":1699,"topicName":"Series","topicDescription":null,"topicUniqueName":null,"chapter":198,"published_at":"2021-08-28T07:49:51.000Z","created_at":"2021-08-28T07:49:50.000Z","updated_at":"2021-11-10T06:29:49.000Z"},{"id":1700,"topicName":"Mensuration and geometry","topicDescription":null,"topicUniqueName":null,"chapter":198,"published_at":"2021-08-28T07:50:14.000Z","created_at":"2021-08-28T07:50:12.000Z","updated_at":"2021-11-10T06:30:06.000Z"},{"id":1701,"topicName":"Elementary statistics","topicDescription":null,"topicUniqueName":null,"chapter":198,"published_at":"2021-08-28T07:50:35.000Z","created_at":"2021-08-28T07:50:33.000Z","updated_at":"2021-11-10T06:30:17.000Z"},{"id":1702,"topicName":"Probability","topicDescription":null,"topicUniqueName":null,"chapter":198,"published_at":"2021-08-28T07:50:54.000Z","created_at":"2021-08-28T07:50:53.000Z","updated_at":"2021-11-10T06:30:31.000Z"},{"id":1703,"topicName":"Logic: deduction and induction","topicDescription":null,"topicUniqueName":null,"chapter":199,"published_at":"2021-08-28T07:52:39.000Z","created_at":"2021-08-28T07:52:37.000Z","updated_at":"2021-11-10T06:31:11.000Z"},{"id":1704,"topicName":"Analogy","topicDescription":null,"topicUniqueName":null,"chapter":199,"published_at":"2021-08-28T07:53:02.000Z","created_at":"2021-08-28T07:53:00.000Z","updated_at":"2021-11-10T06:31:26.000Z"},{"id":1705,"topicName":"Numerical relations and reasoning","topicDescription":null,"topicUniqueName":null,"chapter":199,"published_at":"2021-08-28T07:53:26.000Z","created_at":"2021-08-28T07:53:24.000Z","updated_at":"2021-11-10T06:31:41.000Z"},{"id":1706,"topicName":"Numerical relations and reasoning","topicDescription":null,"topicUniqueName":null,"chapter":199,"published_at":"2021-08-28T07:55:24.000Z","created_at":"2021-08-28T07:55:22.000Z","updated_at":"2021-11-10T06:31:50.000Z"},{"id":1707,"topicName":"Transformation of shapes","topicDescription":null,"topicUniqueName":null,"chapter":200,"published_at":"2021-08-28T07:55:50.000Z","created_at":"2021-08-28T07:55:47.000Z","updated_at":"2021-11-10T06:32:24.000Z"},{"id":1708,"topicName":"Translation","topicDescription":null,"topicUniqueName":null,"chapter":200,"published_at":"2021-08-28T07:56:12.000Z","created_at":"2021-08-28T07:56:10.000Z","updated_at":"2021-11-10T06:32:36.000Z"},{"id":1709,"topicName":"Rotation","topicDescription":null,"topicUniqueName":null,"chapter":200,"published_at":"2021-08-28T07:56:30.000Z","created_at":"2021-08-28T07:56:28.000Z","updated_at":"2021-11-10T06:32:47.000Z"},{"id":1710,"topicName":"Scaling","topicDescription":null,"topicUniqueName":null,"chapter":200,"published_at":"2021-08-28T07:57:04.000Z","created_at":"2021-08-28T07:57:01.000Z","updated_at":"2021-11-10T06:33:05.000Z"},{"id":1711,"topicName":"Mirroring","topicDescription":null,"topicUniqueName":null,"chapter":200,"published_at":"2021-08-28T07:57:27.000Z","created_at":"2021-08-28T07:57:24.000Z","updated_at":"2021-11-10T06:33:21.000Z"},{"id":1712,"topicName":"Assembling","topicDescription":null,"topicUniqueName":null,"chapter":200,"published_at":"2021-08-28T07:57:50.000Z","created_at":"2021-08-28T07:57:48.000Z","updated_at":"2021-11-10T06:33:33.000Z"},{"id":1713,"topicName":"Grouping","topicDescription":null,"topicUniqueName":null,"chapter":200,"published_at":"2021-08-28T07:58:12.000Z","created_at":"2021-08-28T07:58:10.000Z","updated_at":"2021-11-10T06:33:45.000Z"},{"id":1714,"topicName":"Paper folding","topicDescription":null,"topicUniqueName":null,"chapter":200,"published_at":"2021-08-28T07:58:33.000Z","created_at":"2021-08-28T07:58:31.000Z","updated_at":"2021-11-10T06:33:55.000Z"},{"id":1715,"topicName":"Cutting","topicDescription":null,"topicUniqueName":null,"chapter":200,"published_at":"2021-08-28T07:58:55.000Z","created_at":"2021-08-28T07:58:53.000Z","updated_at":"2021-11-10T06:34:08.000Z"},{"id":1716,"topicName":"Patterns in 2 and 3 dimensions","topicDescription":null,"topicUniqueName":null,"chapter":200,"published_at":"2021-08-28T07:59:21.000Z","created_at":"2021-08-28T07:59:19.000Z","updated_at":"2021-11-10T06:34:17.000Z"},{"id":1447,"topicName":"Matrix algebra","topicDescription":null,"topicUniqueName":null,"chapter":174,"published_at":"2021-08-27T15:09:00.000Z","created_at":"2021-08-27T15:08:56.000Z","updated_at":"2021-11-10T06:35:15.000Z"},{"id":1448,"topicName":"Systems of linear equations","topicDescription":null,"topicUniqueName":null,"chapter":174,"published_at":"2021-08-27T15:09:46.000Z","created_at":"2021-08-27T15:09:43.000Z","updated_at":"2021-11-10T06:35:34.000Z"},{"id":1449,"topicName":"Eigen values","topicDescription":null,"topicUniqueName":null,"chapter":174,"published_at":"2021-08-27T15:18:19.000Z","created_at":"2021-08-27T15:18:17.000Z","updated_at":"2021-11-10T06:35:51.000Z"},{"id":1450,"topicName":"Eigen vectors","topicDescription":null,"topicUniqueName":null,"chapter":174,"published_at":"2021-08-27T15:18:50.000Z","created_at":"2021-08-27T15:18:48.000Z","updated_at":"2021-11-10T06:36:03.000Z"},{"id":1451,"topicName":"Functions of single variable","topicDescription":null,"topicUniqueName":null,"chapter":175,"published_at":"2021-08-27T15:21:51.000Z","created_at":"2021-08-27T15:21:48.000Z","updated_at":"2021-11-10T06:37:20.000Z"},{"id":1452,"topicName":"Limit","topicDescription":null,"topicUniqueName":null,"chapter":175,"published_at":"2021-08-27T15:22:21.000Z","created_at":"2021-08-27T15:22:19.000Z","updated_at":"2021-11-10T06:37:38.000Z"},{"id":1453,"topicName":"Continuity ","topicDescription":null,"topicUniqueName":null,"chapter":175,"published_at":"2021-08-27T15:23:51.000Z","created_at":"2021-08-27T15:23:49.000Z","updated_at":"2021-11-10T06:37:51.000Z"},{"id":1454,"topicName":"Differentiability","topicDescription":null,"topicUniqueName":null,"chapter":175,"published_at":"2021-08-27T15:24:19.000Z","created_at":"2021-08-27T15:24:17.000Z","updated_at":"2021-11-10T06:38:02.000Z"},{"id":1455,"topicName":"Mean value theorems","topicDescription":null,"topicUniqueName":null,"chapter":175,"published_at":"2021-08-27T15:24:49.000Z","created_at":"2021-08-27T15:24:47.000Z","updated_at":"2021-11-10T06:38:23.000Z"},{"id":1457,"topicName":"Evaluation of definite integrals","topicDescription":null,"topicUniqueName":null,"chapter":175,"published_at":"2021-08-27T15:26:16.000Z","created_at":"2021-08-27T15:26:14.000Z","updated_at":"2021-11-10T06:38:48.000Z"},{"id":1458,"topicName":"Evaluation of improper integrals","topicDescription":null,"topicUniqueName":null,"chapter":175,"published_at":"2021-08-27T15:27:00.000Z","created_at":"2021-08-27T15:26:57.000Z","updated_at":"2021-11-10T06:39:04.000Z"},{"id":1460,"topicName":"Partial derivatives","topicDescription":null,"topicUniqueName":null,"chapter":175,"published_at":"2021-08-27T15:27:53.000Z","created_at":"2021-08-27T15:27:51.000Z","updated_at":"2021-11-10T06:39:26.000Z"},{"id":1461,"topicName":"Total derivative","topicDescription":null,"topicUniqueName":null,"chapter":175,"published_at":"2021-08-27T15:28:32.000Z","created_at":"2021-08-27T15:28:30.000Z","updated_at":"2021-11-10T06:39:41.000Z"},{"id":1463,"topicName":"Maxima and minima","topicDescription":null,"topicUniqueName":null,"chapter":175,"published_at":"2021-08-27T15:29:22.000Z","created_at":"2021-08-27T15:29:20.000Z","updated_at":"2021-11-10T06:40:07.000Z"},{"id":1465,"topicName":"Gradient","topicDescription":null,"topicUniqueName":null,"chapter":175,"published_at":"2021-08-27T15:30:09.000Z","created_at":"2021-08-27T15:30:08.000Z","updated_at":"2021-11-10T06:40:30.000Z"},{"id":1466,"topicName":"Divergence ","topicDescription":null,"topicUniqueName":null,"chapter":175,"published_at":"2021-08-27T15:31:20.000Z","created_at":"2021-08-27T15:31:18.000Z","updated_at":"2021-11-10T06:41:17.000Z"},{"id":1467,"topicName":"Curl","topicDescription":null,"topicUniqueName":null,"chapter":175,"published_at":"2021-08-27T15:31:48.000Z","created_at":"2021-08-27T15:31:45.000Z","updated_at":"2021-11-10T06:41:36.000Z"},{"id":1468,"topicName":"Vector identities","topicDescription":null,"topicUniqueName":null,"chapter":175,"published_at":"2021-08-27T15:32:14.000Z","created_at":"2021-08-27T15:32:12.000Z","updated_at":"2021-11-10T06:42:09.000Z"},{"id":1469,"topicName":"Directional derivatives","topicDescription":null,"topicUniqueName":null,"chapter":175,"published_at":"2021-08-27T15:32:46.000Z","created_at":"2021-08-27T15:32:44.000Z","updated_at":"2021-11-10T06:42:30.000Z"},{"id":1470,"topicName":"Line, surface and volume integrals","topicDescription":null,"topicUniqueName":null,"chapter":175,"published_at":"2021-08-27T15:33:27.000Z","created_at":"2021-08-27T15:33:25.000Z","updated_at":"2021-11-10T06:42:59.000Z"},{"id":1472,"topicName":"Stokes theorem","topicDescription":null,"topicUniqueName":null,"chapter":175,"published_at":"2021-08-27T15:34:20.000Z","created_at":"2021-08-27T15:34:18.000Z","updated_at":"2021-11-10T06:43:19.000Z"},{"id":6697,"topicName":" Gauss’s theorem","topicDescription":null,"topicUniqueName":null,"chapter":175,"published_at":"2021-10-30T11:01:31.000Z","created_at":"2021-10-30T11:01:31.000Z","updated_at":"2021-11-10T06:43:39.000Z"},{"id":1473,"topicName":"Green’s theorem","topicDescription":null,"topicUniqueName":null,"chapter":175,"published_at":"2021-08-27T15:34:46.000Z","created_at":"2021-08-27T15:34:43.000Z","updated_at":"2021-11-10T07:08:20.000Z"},{"id":1474,"topicName":"First order equations (linear and nonlinear)","topicDescription":null,"topicUniqueName":null,"chapter":176,"published_at":"2021-08-27T15:38:26.000Z","created_at":"2021-08-27T15:38:24.000Z","updated_at":"2021-11-10T07:09:02.000Z"},{"id":1475,"topicName":"Higher order linear differential equations with constant coefficients","topicDescription":null,"topicUniqueName":null,"chapter":176,"published_at":"2021-08-27T15:39:01.000Z","created_at":"2021-08-27T15:38:59.000Z","updated_at":"2021-11-10T07:09:18.000Z"},{"id":1476,"topicName":"Euler-Cauchy equation","topicDescription":null,"topicUniqueName":null,"chapter":176,"published_at":"2021-08-27T15:39:35.000Z","created_at":"2021-08-27T15:39:33.000Z","updated_at":"2021-11-10T07:09:28.000Z"},{"id":1477,"topicName":"Initial and boundary value problems","topicDescription":null,"topicUniqueName":null,"chapter":176,"published_at":"2021-08-27T15:40:04.000Z","created_at":"2021-08-27T15:40:01.000Z","updated_at":"2021-11-10T07:09:47.000Z"},{"id":1478,"topicName":"Laplace transforms","topicDescription":null,"topicUniqueName":null,"chapter":176,"published_at":"2021-08-27T15:40:34.000Z","created_at":"2021-08-27T15:40:30.000Z","updated_at":"2021-11-10T07:10:13.000Z"},{"id":1482,"topicName":"Analytic functions","topicDescription":null,"topicUniqueName":null,"chapter":177,"published_at":"2021-08-27T15:47:13.000Z","created_at":"2021-08-27T15:47:11.000Z","updated_at":"2021-11-10T07:10:50.000Z"},{"id":1484,"topicName":"Cauchy’s integral theorem","topicDescription":null,"topicUniqueName":null,"chapter":177,"published_at":"2021-08-27T15:48:02.000Z","created_at":"2021-08-27T15:48:00.000Z","updated_at":"2021-11-10T07:11:07.000Z"},{"id":1486,"topicName":"Taylor series","topicDescription":null,"topicUniqueName":null,"chapter":177,"published_at":"2021-08-27T15:48:53.000Z","created_at":"2021-08-27T15:48:51.000Z","updated_at":"2021-11-10T07:11:28.000Z"},{"id":1488,"topicName":"Definitions of probability","topicDescription":null,"topicUniqueName":null,"chapter":178,"published_at":"2021-08-27T15:51:58.000Z","created_at":"2021-08-27T15:51:56.000Z","updated_at":"2021-11-10T07:12:05.000Z"},{"id":1489,"topicName":"Sampling theorems","topicDescription":null,"topicUniqueName":null,"chapter":178,"published_at":"2021-08-27T15:52:31.000Z","created_at":"2021-08-27T15:52:29.000Z","updated_at":"2021-11-10T07:12:15.000Z"},{"id":1490,"topicName":"Conditional probability","topicDescription":null,"topicUniqueName":null,"chapter":178,"published_at":"2021-08-27T15:52:59.000Z","created_at":"2021-08-27T15:52:57.000Z","updated_at":"2021-11-10T07:12:33.000Z"},{"id":1491,"topicName":"Mean deviation","topicDescription":null,"topicUniqueName":null,"chapter":178,"published_at":"2021-08-27T15:55:04.000Z","created_at":"2021-08-27T15:55:02.000Z","updated_at":"2021-11-10T07:12:44.000Z"},{"id":1492,"topicName":"Median deviation","topicDescription":null,"topicUniqueName":null,"chapter":178,"published_at":"2021-08-27T15:55:30.000Z","created_at":"2021-08-27T15:55:28.000Z","updated_at":"2021-11-10T07:12:53.000Z"},{"id":1493,"topicName":"Mode deviation","topicDescription":null,"topicUniqueName":null,"chapter":178,"published_at":"2021-08-27T15:55:59.000Z","created_at":"2021-08-27T15:55:57.000Z","updated_at":"2021-11-10T07:13:03.000Z"},{"id":1494,"topicName":"Standard deviation","topicDescription":null,"topicUniqueName":null,"chapter":178,"published_at":"2021-08-27T15:56:56.000Z","created_at":"2021-08-27T15:56:53.000Z","updated_at":"2021-11-10T07:13:26.000Z"},{"id":1723,"topicName":"Linear regression","topicDescription":null,"topicUniqueName":null,"chapter":178,"published_at":"2021-08-31T17:17:48.000Z","created_at":"2021-08-31T17:17:46.000Z","updated_at":"2021-11-10T07:13:48.000Z"},{"id":1495,"topicName":"Random variables","topicDescription":null,"topicUniqueName":null,"chapter":178,"published_at":"2021-08-27T15:57:32.000Z","created_at":"2021-08-27T15:57:27.000Z","updated_at":"2021-11-10T07:14:05.000Z"},{"id":1497,"topicName":"Poisson distributions","topicDescription":null,"topicUniqueName":null,"chapter":178,"published_at":"2021-08-27T15:58:36.000Z","created_at":"2021-08-27T15:58:34.000Z","updated_at":"2021-11-10T07:14:24.000Z"},{"id":1498,"topicName":"Normal distributions","topicDescription":null,"topicUniqueName":null,"chapter":178,"published_at":"2021-08-27T15:59:07.000Z","created_at":"2021-08-27T15:59:02.000Z","updated_at":"2021-11-10T07:14:38.000Z"},{"id":1496,"topicName":"Binomial distributions","topicDescription":null,"topicUniqueName":null,"chapter":178,"published_at":"2021-08-27T15:58:08.000Z","created_at":"2021-08-27T15:58:02.000Z","updated_at":"2021-11-10T07:14:59.000Z"},{"id":2235,"topicName":"Exponential distributions","topicDescription":null,"topicUniqueName":null,"chapter":178,"published_at":"2021-09-03T17:28:16.000Z","created_at":"2021-09-03T17:28:12.000Z","updated_at":"2021-11-10T07:15:20.000Z"},{"id":1499,"topicName":"Numerical solutions of linear algebraic equations","topicDescription":null,"topicUniqueName":null,"chapter":179,"published_at":"2021-08-27T16:02:22.000Z","created_at":"2021-08-27T16:02:20.000Z","updated_at":"2021-11-10T07:16:13.000Z"},{"id":1500,"topicName":"Numerical solutions of non-linear algebraic equations","topicDescription":null,"topicUniqueName":null,"chapter":179,"published_at":"2021-08-27T16:02:52.000Z","created_at":"2021-08-27T16:02:49.000Z","updated_at":"2021-11-10T07:16:25.000Z"},{"id":1501,"topicName":"Integration by trapezoidal","topicDescription":null,"topicUniqueName":null,"chapter":179,"published_at":"2021-08-27T16:03:24.000Z","created_at":"2021-08-27T16:03:18.000Z","updated_at":"2021-11-10T07:16:49.000Z"},{"id":1502,"topicName":"Simpson’s rules","topicDescription":null,"topicUniqueName":null,"chapter":179,"published_at":"2021-08-27T16:03:56.000Z","created_at":"2021-08-27T16:03:53.000Z","updated_at":"2021-11-10T07:17:05.000Z"},{"id":1503,"topicName":"Single and multi-step methods for differential equations","topicDescription":null,"topicUniqueName":null,"chapter":179,"published_at":"2021-08-27T16:04:30.000Z","created_at":"2021-08-27T16:04:27.000Z","updated_at":"2021-11-10T07:17:25.000Z"},{"id":6856,"topicName":"Structure- physical and mechanical properties","topicDescription":null,"topicUniqueName":null,"chapter":591,"published_at":"2021-11-10T07:20:28.000Z","created_at":"2021-11-10T07:20:28.000Z","updated_at":"2021-11-10T07:20:28.000Z"},{"id":6857,"topicName":"Applications of common engineering materials (metals and alloys/semiconductors/ceramics/polymers and composites – metal/polymer and ceramic based)","topicDescription":null,"topicUniqueName":null,"chapter":591,"published_at":"2021-11-10T07:20:28.000Z","created_at":"2021-11-10T07:20:28.000Z","updated_at":"2021-11-10T07:20:28.000Z"},{"id":6858,"topicName":"Iron-carbon equilibrium phase diagram","topicDescription":null,"topicUniqueName":null,"chapter":591,"published_at":"2021-11-10T07:20:28.000Z","created_at":"2021-11-10T07:20:28.000Z","updated_at":"2021-11-10T07:20:28.000Z"},{"id":6859,"topicName":"Heat treatment of metals and alloys and its influence on mechanical properties","topicDescription":null,"topicUniqueName":null,"chapter":591,"published_at":"2021-11-10T07:20:28.000Z","created_at":"2021-11-10T07:20:28.000Z","updated_at":"2021-11-10T07:20:28.000Z"},{"id":6860,"topicName":"Stress-strain behavior of metals and alloys","topicDescription":null,"topicUniqueName":null,"chapter":591,"published_at":"2021-11-10T07:20:28.000Z","created_at":"2021-11-10T07:20:28.000Z","updated_at":"2021-11-10T07:20:28.000Z"},{"id":6861,"topicName":"Engineering mechanics","topicDescription":null,"topicUniqueName":null,"chapter":592,"published_at":"2021-11-10T07:23:08.000Z","created_at":"2021-11-10T07:23:08.000Z","updated_at":"2021-11-10T07:23:08.000Z"},{"id":6862,"topicName":"Equivalent force systems","topicDescription":null,"topicUniqueName":null,"chapter":592,"published_at":"2021-11-10T07:23:08.000Z","created_at":"2021-11-10T07:23:08.000Z","updated_at":"2021-11-10T07:23:08.000Z"},{"id":6863,"topicName":"Free body concepts","topicDescription":null,"topicUniqueName":null,"chapter":592,"published_at":"2021-11-10T07:23:08.000Z","created_at":"2021-11-10T07:23:08.000Z","updated_at":"2021-11-10T07:23:08.000Z"},{"id":6864,"topicName":"Equations of equilibrium","topicDescription":null,"topicUniqueName":null,"chapter":592,"published_at":"2021-11-10T07:23:08.000Z","created_at":"2021-11-10T07:23:08.000Z","updated_at":"2021-11-10T07:23:08.000Z"},{"id":6865,"topicName":"Trusses","topicDescription":null,"topicUniqueName":null,"chapter":592,"published_at":"2021-11-10T07:23:08.000Z","created_at":"2021-11-10T07:23:08.000Z","updated_at":"2021-11-10T07:23:08.000Z"},{"id":6866,"topicName":"Strength of materials","topicDescription":null,"topicUniqueName":null,"chapter":592,"published_at":"2021-11-10T07:23:08.000Z","created_at":"2021-11-10T07:23:08.000Z","updated_at":"2021-11-10T07:23:08.000Z"},{"id":6867,"topicName":"Stress- strain and their relationship","topicDescription":null,"topicUniqueName":null,"chapter":592,"published_at":"2021-11-10T07:23:09.000Z","created_at":"2021-11-10T07:23:09.000Z","updated_at":"2021-11-10T07:23:09.000Z"},{"id":6868,"topicName":"Failure theories","topicDescription":null,"topicUniqueName":null,"chapter":592,"published_at":"2021-11-10T07:23:09.000Z","created_at":"2021-11-10T07:23:09.000Z","updated_at":"2021-11-10T07:23:09.000Z"},{"id":6869,"topicName":"Mohr’s circle (stress)","topicDescription":null,"topicUniqueName":null,"chapter":592,"published_at":"2021-11-10T07:23:09.000Z","created_at":"2021-11-10T07:23:09.000Z","updated_at":"2021-11-10T07:23:09.000Z"},{"id":6870,"topicName":"Deflection of beams","topicDescription":null,"topicUniqueName":null,"chapter":592,"published_at":"2021-11-10T07:23:09.000Z","created_at":"2021-11-10T07:23:09.000Z","updated_at":"2021-11-10T07:23:09.000Z"},{"id":6871,"topicName":"Bending and shear stresses","topicDescription":null,"topicUniqueName":null,"chapter":592,"published_at":"2021-11-10T07:23:09.000Z","created_at":"2021-11-10T07:23:09.000Z","updated_at":"2021-11-10T07:23:09.000Z"},{"id":6872,"topicName":"Euler’s theory of columns","topicDescription":null,"topicUniqueName":null,"chapter":592,"published_at":"2021-11-10T07:23:09.000Z","created_at":"2021-11-10T07:23:09.000Z","updated_at":"2021-11-10T07:23:09.000Z"},{"id":6873,"topicName":"Thick and thin cylinders","topicDescription":null,"topicUniqueName":null,"chapter":592,"published_at":"2021-11-10T07:23:10.000Z","created_at":"2021-11-10T07:23:10.000Z","updated_at":"2021-11-10T07:23:10.000Z"},{"id":6874,"topicName":"Torsion","topicDescription":null,"topicUniqueName":null,"chapter":592,"published_at":"2021-11-10T07:23:10.000Z","created_at":"2021-11-10T07:23:10.000Z","updated_at":"2021-11-10T07:23:10.000Z"},{"id":6875,"topicName":"Analysis of planar mechanisms. cams and followers","topicDescription":null,"topicUniqueName":null,"chapter":593,"published_at":"2021-11-10T07:25:40.000Z","created_at":"2021-11-10T07:25:40.000Z","updated_at":"2021-11-10T07:25:40.000Z"},{"id":6876,"topicName":"Governors and fly wheels","topicDescription":null,"topicUniqueName":null,"chapter":593,"published_at":"2021-11-10T07:25:40.000Z","created_at":"2021-11-10T07:25:40.000Z","updated_at":"2021-11-10T07:25:40.000Z"},{"id":6877,"topicName":"Design of bolted-Riveted and welded joints","topicDescription":null,"topicUniqueName":null,"chapter":593,"published_at":"2021-11-10T07:25:41.000Z","created_at":"2021-11-10T07:25:41.000Z","updated_at":"2021-11-10T07:25:41.000Z"},{"id":6878,"topicName":"Interference/shrink fit joints","topicDescription":null,"topicUniqueName":null,"chapter":593,"published_at":"2021-11-10T07:25:41.000Z","created_at":"2021-11-10T07:25:41.000Z","updated_at":"2021-11-10T07:25:41.000Z"},{"id":6879,"topicName":"Friction and lubrication","topicDescription":null,"topicUniqueName":null,"chapter":593,"published_at":"2021-11-10T07:25:41.000Z","created_at":"2021-11-10T07:25:41.000Z","updated_at":"2021-11-10T07:25:41.000Z"},{"id":6880,"topicName":"Design of shafts","topicDescription":null,"topicUniqueName":null,"chapter":593,"published_at":"2021-11-10T07:25:41.000Z","created_at":"2021-11-10T07:25:41.000Z","updated_at":"2021-11-10T07:25:41.000Z"},{"id":6881,"topicName":"Keys","topicDescription":null,"topicUniqueName":null,"chapter":593,"published_at":"2021-11-10T07:25:41.000Z","created_at":"2021-11-10T07:25:41.000Z","updated_at":"2021-11-10T07:25:41.000Z"},{"id":6882,"topicName":"Couplings","topicDescription":null,"topicUniqueName":null,"chapter":593,"published_at":"2021-11-10T07:25:41.000Z","created_at":"2021-11-10T07:25:41.000Z","updated_at":"2021-11-10T07:25:41.000Z"},{"id":6883,"topicName":"Spur gears","topicDescription":null,"topicUniqueName":null,"chapter":593,"published_at":"2021-11-10T07:25:42.000Z","created_at":"2021-11-10T07:25:42.000Z","updated_at":"2021-11-10T07:25:42.000Z"},{"id":6884,"topicName":"Belt drives","topicDescription":null,"topicUniqueName":null,"chapter":593,"published_at":"2021-11-10T07:25:42.000Z","created_at":"2021-11-10T07:25:42.000Z","updated_at":"2021-11-10T07:25:42.000Z"},{"id":6885,"topicName":"Brakes and clutches","topicDescription":null,"topicUniqueName":null,"chapter":593,"published_at":"2021-11-10T07:25:42.000Z","created_at":"2021-11-10T07:25:42.000Z","updated_at":"2021-11-10T07:25:42.000Z"},{"id":6886,"topicName":"Pressure vessels","topicDescription":null,"topicUniqueName":null,"chapter":593,"published_at":"2021-11-10T07:25:42.000Z","created_at":"2021-11-10T07:25:42.000Z","updated_at":"2021-11-10T07:25:42.000Z"},{"id":6887,"topicName":"Fluid mechanics","topicDescription":null,"topicUniqueName":null,"chapter":594,"published_at":"2021-11-10T07:29:15.000Z","created_at":"2021-11-10T07:29:15.000Z","updated_at":"2021-11-10T07:29:15.000Z"},{"id":6888,"topicName":"Fluid statics","topicDescription":null,"topicUniqueName":null,"chapter":594,"published_at":"2021-11-10T07:29:15.000Z","created_at":"2021-11-10T07:29:15.000Z","updated_at":"2021-11-10T07:29:15.000Z"},{"id":6889,"topicName":"Bernoulli’s equation","topicDescription":null,"topicUniqueName":null,"chapter":594,"published_at":"2021-11-10T07:29:15.000Z","created_at":"2021-11-10T07:29:15.000Z","updated_at":"2021-11-10T07:29:15.000Z"},{"id":6890,"topicName":"Flow through pipes","topicDescription":null,"topicUniqueName":null,"chapter":594,"published_at":"2021-11-10T07:29:15.000Z","created_at":"2021-11-10T07:29:15.000Z","updated_at":"2021-11-10T07:29:15.000Z"},{"id":6891,"topicName":"Laminar and turbulent flows","topicDescription":null,"topicUniqueName":null,"chapter":594,"published_at":"2021-11-10T07:29:15.000Z","created_at":"2021-11-10T07:29:15.000Z","updated_at":"2021-11-10T07:29:15.000Z"},{"id":6892,"topicName":"Equations of continuity and momentum","topicDescription":null,"topicUniqueName":null,"chapter":594,"published_at":"2021-11-10T07:29:15.000Z","created_at":"2021-11-10T07:29:15.000Z","updated_at":"2021-11-10T07:29:15.000Z"},{"id":6893,"topicName":"Capillary action","topicDescription":null,"topicUniqueName":null,"chapter":594,"published_at":"2021-11-10T07:29:16.000Z","created_at":"2021-11-10T07:29:16.000Z","updated_at":"2021-11-10T07:29:16.000Z"},{"id":6894,"topicName":"Dimensional analysis","topicDescription":null,"topicUniqueName":null,"chapter":594,"published_at":"2021-11-10T07:29:16.000Z","created_at":"2021-11-10T07:29:16.000Z","updated_at":"2021-11-10T07:29:16.000Z"},{"id":6895,"topicName":"Thermodynamics","topicDescription":null,"topicUniqueName":null,"chapter":594,"published_at":"2021-11-10T07:29:16.000Z","created_at":"2021-11-10T07:29:16.000Z","updated_at":"2021-11-10T07:29:16.000Z"},{"id":6896,"topicName":"zeroth - first and second laws of thermodynamics","topicDescription":null,"topicUniqueName":null,"chapter":594,"published_at":"2021-11-10T07:29:16.000Z","created_at":"2021-11-10T07:29:16.000Z","updated_at":"2021-11-10T07:29:16.000Z"},{"id":6897,"topicName":"Thermodynamic systems and processes","topicDescription":null,"topicUniqueName":null,"chapter":594,"published_at":"2021-11-10T07:29:17.000Z","created_at":"2021-11-10T07:29:17.000Z","updated_at":"2021-11-10T07:29:17.000Z"},{"id":6898,"topicName":"Calculation of work and heat for systems and control volumes","topicDescription":null,"topicUniqueName":null,"chapter":594,"published_at":"2021-11-10T07:29:17.000Z","created_at":"2021-11-10T07:29:17.000Z","updated_at":"2021-11-10T07:29:17.000Z"},{"id":6899,"topicName":"Air standard cycles","topicDescription":null,"topicUniqueName":null,"chapter":594,"published_at":"2021-11-10T07:29:17.000Z","created_at":"2021-11-10T07:29:17.000Z","updated_at":"2021-11-10T07:29:17.000Z"},{"id":6900,"topicName":"Heat transfer – basic applications of conduction- convection and radiation","topicDescription":null,"topicUniqueName":null,"chapter":594,"published_at":"2021-11-10T07:29:17.000Z","created_at":"2021-11-10T07:29:17.000Z","updated_at":"2021-11-10T07:29:17.000Z"},{"id":6901,"topicName":"Types of casting processes and applications","topicDescription":null,"topicUniqueName":null,"chapter":595,"published_at":"2021-11-10T07:32:34.000Z","created_at":"2021-11-10T07:32:34.000Z","updated_at":"2021-11-10T07:32:34.000Z"},{"id":6902,"topicName":"Sand casting","topicDescription":null,"topicUniqueName":null,"chapter":595,"published_at":"2021-11-10T07:32:34.000Z","created_at":"2021-11-10T07:32:34.000Z","updated_at":"2021-11-10T07:32:34.000Z"},{"id":6903,"topicName":"Patterns: types / materials and allowances","topicDescription":null,"topicUniqueName":null,"chapter":595,"published_at":"2021-11-10T07:32:34.000Z","created_at":"2021-11-10T07:32:34.000Z","updated_at":"2021-11-10T07:32:34.000Z"},{"id":6904,"topicName":"Molds and cores: materials/ making and testing","topicDescription":null,"topicUniqueName":null,"chapter":595,"published_at":"2021-11-10T07:32:34.000Z","created_at":"2021-11-10T07:32:34.000Z","updated_at":"2021-11-10T07:32:34.000Z"},{"id":6905,"topicName":"Design of gating system and riser","topicDescription":null,"topicUniqueName":null,"chapter":595,"published_at":"2021-11-10T07:32:34.000Z","created_at":"2021-11-10T07:32:34.000Z","updated_at":"2021-11-10T07:32:34.000Z"},{"id":6906,"topicName":"Casting techniques of cast iron-steels and nonferrous metals and alloys","topicDescription":null,"topicUniqueName":null,"chapter":595,"published_at":"2021-11-10T07:32:35.000Z","created_at":"2021-11-10T07:32:35.000Z","updated_at":"2021-11-10T07:32:35.000Z"},{"id":6907,"topicName":"Analysis of solidification and microstructure development","topicDescription":null,"topicUniqueName":null,"chapter":595,"published_at":"2021-11-10T07:32:35.000Z","created_at":"2021-11-10T07:32:35.000Z","updated_at":"2021-11-10T07:32:35.000Z"},{"id":6908,"topicName":"Other casting techniques","topicDescription":null,"topicUniqueName":null,"chapter":595,"published_at":"2021-11-10T07:32:35.000Z","created_at":"2021-11-10T07:32:35.000Z","updated_at":"2021-11-10T07:32:35.000Z"},{"id":6909,"topicName":"Pressure die casting","topicDescription":null,"topicUniqueName":null,"chapter":595,"published_at":"2021-11-10T07:32:35.000Z","created_at":"2021-11-10T07:32:35.000Z","updated_at":"2021-11-10T07:32:35.000Z"},{"id":6910,"topicName":"Centrifugal casting","topicDescription":null,"topicUniqueName":null,"chapter":595,"published_at":"2021-11-10T07:32:35.000Z","created_at":"2021-11-10T07:32:35.000Z","updated_at":"2021-11-10T07:32:35.000Z"},{"id":6911,"topicName":"Investment casting","topicDescription":null,"topicUniqueName":null,"chapter":595,"published_at":"2021-11-10T07:32:35.000Z","created_at":"2021-11-10T07:32:35.000Z","updated_at":"2021-11-10T07:32:35.000Z"},{"id":6912,"topicName":"Shell mold casting","topicDescription":null,"topicUniqueName":null,"chapter":595,"published_at":"2021-11-10T07:32:36.000Z","created_at":"2021-11-10T07:32:36.000Z","updated_at":"2021-11-10T07:32:36.000Z"},{"id":6913,"topicName":"Casting defects and their inspection by nondestructive testing","topicDescription":null,"topicUniqueName":null,"chapter":595,"published_at":"2021-11-10T07:32:36.000Z","created_at":"2021-11-10T07:32:36.000Z","updated_at":"2021-11-10T07:32:36.000Z"},{"id":6914,"topicName":"Stress-strain relations in elastic and plastic deformation","topicDescription":null,"topicUniqueName":null,"chapter":596,"published_at":"2021-11-10T07:35:33.000Z","created_at":"2021-11-10T07:35:33.000Z","updated_at":"2021-11-10T07:35:33.000Z"},{"id":6915,"topicName":"Von Mises and Tresca yield criteria","topicDescription":null,"topicUniqueName":null,"chapter":596,"published_at":"2021-11-10T07:35:33.000Z","created_at":"2021-11-10T07:35:33.000Z","updated_at":"2021-11-10T07:35:33.000Z"},{"id":6916,"topicName":"Concept of flow stress","topicDescription":null,"topicUniqueName":null,"chapter":596,"published_at":"2021-11-10T07:35:33.000Z","created_at":"2021-11-10T07:35:33.000Z","updated_at":"2021-11-10T07:35:33.000Z"},{"id":6917,"topicName":"Hot- warm and cold working","topicDescription":null,"topicUniqueName":null,"chapter":596,"published_at":"2021-11-10T07:35:33.000Z","created_at":"2021-11-10T07:35:33.000Z","updated_at":"2021-11-10T07:35:33.000Z"},{"id":6918,"topicName":"Bulk forming processes: forging - rolling - extrusion and wire drawing","topicDescription":null,"topicUniqueName":null,"chapter":596,"published_at":"2021-11-10T07:35:33.000Z","created_at":"2021-11-10T07:35:33.000Z","updated_at":"2021-11-10T07:35:33.000Z"},{"id":6919,"topicName":"Sheet metal working processes : blanking- punching- bending- stretch forming- spinning and deep drawing","topicDescription":null,"topicUniqueName":null,"chapter":596,"published_at":"2021-11-10T07:35:34.000Z","created_at":"2021-11-10T07:35:34.000Z","updated_at":"2021-11-10T07:35:34.000Z"},{"id":6920,"topicName":"Ideal work and slab analysis","topicDescription":null,"topicUniqueName":null,"chapter":596,"published_at":"2021-11-10T07:35:34.000Z","created_at":"2021-11-10T07:35:34.000Z","updated_at":"2021-11-10T07:35:34.000Z"},{"id":6921,"topicName":"Defects in metal working and their causes","topicDescription":null,"topicUniqueName":null,"chapter":596,"published_at":"2021-11-10T07:35:34.000Z","created_at":"2021-11-10T07:35:34.000Z","updated_at":"2021-11-10T07:35:34.000Z"},{"id":6922,"topicName":"Classification of joining processes","topicDescription":null,"topicUniqueName":null,"chapter":597,"published_at":"2021-11-10T07:37:50.000Z","created_at":"2021-11-10T07:37:50.000Z","updated_at":"2021-11-10T07:37:50.000Z"},{"id":6923,"topicName":"Principles of fusion welding processes using different heat sources (flame/ arc/ resistance/ laser/ electron beam)","topicDescription":null,"topicUniqueName":null,"chapter":597,"published_at":"2021-11-10T07:37:50.000Z","created_at":"2021-11-10T07:37:50.000Z","updated_at":"2021-11-10T07:37:51.000Z"},{"id":6924,"topicName":"Heat transfer and associated losses","topicDescription":null,"topicUniqueName":null,"chapter":597,"published_at":"2021-11-10T07:37:51.000Z","created_at":"2021-11-10T07:37:51.000Z","updated_at":"2021-11-10T07:37:51.000Z"},{"id":6925,"topicName":"Arc welding processes","topicDescription":null,"topicUniqueName":null,"chapter":597,"published_at":"2021-11-10T07:37:51.000Z","created_at":"2021-11-10T07:37:51.000Z","updated_at":"2021-11-10T07:37:51.000Z"},{"id":6926,"topicName":"SMAW","topicDescription":null,"topicUniqueName":null,"chapter":597,"published_at":"2021-11-10T07:37:51.000Z","created_at":"2021-11-10T07:37:51.000Z","updated_at":"2021-11-10T07:37:51.000Z"},{"id":6927,"topicName":" GMAW","topicDescription":null,"topicUniqueName":null,"chapter":597,"published_at":"2021-11-10T07:37:51.000Z","created_at":"2021-11-10T07:37:51.000Z","updated_at":"2021-11-10T07:37:51.000Z"},{"id":6928,"topicName":" GTAW","topicDescription":null,"topicUniqueName":null,"chapter":597,"published_at":"2021-11-10T07:37:51.000Z","created_at":"2021-11-10T07:37:51.000Z","updated_at":"2021-11-10T07:37:51.000Z"},{"id":6929,"topicName":" Plasma arc","topicDescription":null,"topicUniqueName":null,"chapter":597,"published_at":"2021-11-10T07:37:52.000Z","created_at":"2021-11-10T07:37:52.000Z","updated_at":"2021-11-10T07:37:52.000Z"},{"id":6930,"topicName":"Submerged arc welding processes","topicDescription":null,"topicUniqueName":null,"chapter":597,"published_at":"2021-11-10T07:37:52.000Z","created_at":"2021-11-10T07:37:52.000Z","updated_at":"2021-11-10T07:37:52.000Z"},{"id":6931,"topicName":"Principles of solid state welding processes","topicDescription":null,"topicUniqueName":null,"chapter":597,"published_at":"2021-11-10T07:37:52.000Z","created_at":"2021-11-10T07:37:52.000Z","updated_at":"2021-11-10T07:37:52.000Z"},{"id":6932,"topicName":"Friction welding","topicDescription":null,"topicUniqueName":null,"chapter":597,"published_at":"2021-11-10T07:37:52.000Z","created_at":"2021-11-10T07:37:52.000Z","updated_at":"2021-11-10T07:37:52.000Z"},{"id":6933,"topicName":"Friction stir welding","topicDescription":null,"topicUniqueName":null,"chapter":597,"published_at":"2021-11-10T07:37:52.000Z","created_at":"2021-11-10T07:37:52.000Z","updated_at":"2021-11-10T07:37:52.000Z"},{"id":6934,"topicName":"Ultrasonic welding","topicDescription":null,"topicUniqueName":null,"chapter":597,"published_at":"2021-11-10T07:37:52.000Z","created_at":"2021-11-10T07:37:52.000Z","updated_at":"2021-11-10T07:37:52.000Z"},{"id":6935,"topicName":"Welding defects - causes and inspection","topicDescription":null,"topicUniqueName":null,"chapter":597,"published_at":"2021-11-10T07:37:53.000Z","created_at":"2021-11-10T07:37:53.000Z","updated_at":"2021-11-10T07:37:53.000Z"},{"id":6936,"topicName":"Principles of adhesive joining/ brazing and soldering processes","topicDescription":null,"topicUniqueName":null,"chapter":597,"published_at":"2021-11-10T07:37:53.000Z","created_at":"2021-11-10T07:37:53.000Z","updated_at":"2021-11-10T07:37:53.000Z"},{"id":6937,"topicName":"Production of metal/ceramic powders/ compaction and sintering of metals and ceramic powders","topicDescription":null,"topicUniqueName":null,"chapter":598,"published_at":"2021-11-10T07:39:46.000Z","created_at":"2021-11-10T07:39:46.000Z","updated_at":"2021-11-10T07:39:47.000Z"},{"id":6938,"topicName":"Cold and hot isostatic pressing","topicDescription":null,"topicUniqueName":null,"chapter":598,"published_at":"2021-11-10T07:39:47.000Z","created_at":"2021-11-10T07:39:47.000Z","updated_at":"2021-11-10T07:39:47.000Z"},{"id":6939,"topicName":"Polymer processing","topicDescription":null,"topicUniqueName":null,"chapter":599,"published_at":"2021-11-10T07:41:15.000Z","created_at":"2021-11-10T07:41:15.000Z","updated_at":"2021-11-10T07:41:15.000Z"},{"id":6940,"topicName":"Injection","topicDescription":null,"topicUniqueName":null,"chapter":599,"published_at":"2021-11-10T07:41:16.000Z","created_at":"2021-11-10T07:41:16.000Z","updated_at":"2021-11-10T07:41:16.000Z"},{"id":6941,"topicName":"Compression","topicDescription":null,"topicUniqueName":null,"chapter":599,"published_at":"2021-11-10T07:41:16.000Z","created_at":"2021-11-10T07:41:16.000Z","updated_at":"2021-11-10T07:41:16.000Z"},{"id":6942,"topicName":"Blow molding","topicDescription":null,"topicUniqueName":null,"chapter":599,"published_at":"2021-11-10T07:41:16.000Z","created_at":"2021-11-10T07:41:16.000Z","updated_at":"2021-11-10T07:41:16.000Z"},{"id":6943,"topicName":"Extrusion","topicDescription":null,"topicUniqueName":null,"chapter":599,"published_at":"2021-11-10T07:41:16.000Z","created_at":"2021-11-10T07:41:16.000Z","updated_at":"2021-11-10T07:41:16.000Z"},{"id":6944,"topicName":"Calendaring","topicDescription":null,"topicUniqueName":null,"chapter":599,"published_at":"2021-11-10T07:41:16.000Z","created_at":"2021-11-10T07:41:16.000Z","updated_at":"2021-11-10T07:41:16.000Z"},{"id":6945,"topicName":"Thermoforming","topicDescription":null,"topicUniqueName":null,"chapter":599,"published_at":"2021-11-10T07:41:16.000Z","created_at":"2021-11-10T07:41:16.000Z","updated_at":"2021-11-10T07:41:16.000Z"},{"id":6946,"topicName":"Molding of composites","topicDescription":null,"topicUniqueName":null,"chapter":599,"published_at":"2021-11-10T07:41:16.000Z","created_at":"2021-11-10T07:41:16.000Z","updated_at":"2021-11-10T07:41:16.000Z"},{"id":6947,"topicName":"Orthogonal and oblique machining","topicDescription":null,"topicUniqueName":null,"chapter":600,"published_at":"2021-11-10T07:45:56.000Z","created_at":"2021-11-10T07:45:56.000Z","updated_at":"2021-11-10T07:45:56.000Z"},{"id":6948,"topicName":"Single point cutting tool and tool signature","topicDescription":null,"topicUniqueName":null,"chapter":600,"published_at":"2021-11-10T07:45:56.000Z","created_at":"2021-11-10T07:45:56.000Z","updated_at":"2021-11-10T07:45:56.000Z"},{"id":6949,"topicName":"Chip formation","topicDescription":null,"topicUniqueName":null,"chapter":600,"published_at":"2021-11-10T07:45:56.000Z","created_at":"2021-11-10T07:45:56.000Z","updated_at":"2021-11-10T07:45:56.000Z"},{"id":6950,"topicName":"Cutting forces","topicDescription":null,"topicUniqueName":null,"chapter":600,"published_at":"2021-11-10T07:45:56.000Z","created_at":"2021-11-10T07:45:56.000Z","updated_at":"2021-11-10T07:45:56.000Z"},{"id":6951,"topicName":"Merchant’s analysis","topicDescription":null,"topicUniqueName":null,"chapter":600,"published_at":"2021-11-10T07:45:56.000Z","created_at":"2021-11-10T07:45:56.000Z","updated_at":"2021-11-10T07:45:56.000Z"},{"id":6952,"topicName":"Specific cutting energy and power","topicDescription":null,"topicUniqueName":null,"chapter":600,"published_at":"2021-11-10T07:45:56.000Z","created_at":"2021-11-10T07:45:56.000Z","updated_at":"2021-11-10T07:45:56.000Z"},{"id":6953,"topicName":"Machining parameters and material removal rate","topicDescription":null,"topicUniqueName":null,"chapter":600,"published_at":"2021-11-10T07:45:57.000Z","created_at":"2021-11-10T07:45:57.000Z","updated_at":"2021-11-10T07:45:57.000Z"},{"id":6954,"topicName":"Tool materials","topicDescription":null,"topicUniqueName":null,"chapter":600,"published_at":"2021-11-10T07:45:57.000Z","created_at":"2021-11-10T07:45:57.000Z","updated_at":"2021-11-10T07:45:57.000Z"},{"id":6955,"topicName":"Tool wear","topicDescription":null,"topicUniqueName":null,"chapter":600,"published_at":"2021-11-10T07:45:57.000Z","created_at":"2021-11-10T07:45:57.000Z","updated_at":"2021-11-10T07:45:57.000Z"},{"id":6956,"topicName":"Tool life","topicDescription":null,"topicUniqueName":null,"chapter":600,"published_at":"2021-11-10T07:45:57.000Z","created_at":"2021-11-10T07:45:57.000Z","updated_at":"2021-11-10T07:45:57.000Z"},{"id":6957,"topicName":"Thermal aspects of machining","topicDescription":null,"topicUniqueName":null,"chapter":600,"published_at":"2021-11-10T07:45:57.000Z","created_at":"2021-11-10T07:45:57.000Z","updated_at":"2021-11-10T07:45:57.000Z"},{"id":6958,"topicName":"Cutting fluids","topicDescription":null,"topicUniqueName":null,"chapter":600,"published_at":"2021-11-10T07:45:57.000Z","created_at":"2021-11-10T07:45:57.000Z","updated_at":"2021-11-10T07:45:57.000Z"},{"id":6959,"topicName":"Machinability","topicDescription":null,"topicUniqueName":null,"chapter":600,"published_at":"2021-11-10T07:45:58.000Z","created_at":"2021-11-10T07:45:58.000Z","updated_at":"2021-11-10T07:45:58.000Z"},{"id":6960,"topicName":"Economics of machining","topicDescription":null,"topicUniqueName":null,"chapter":600,"published_at":"2021-11-10T07:45:58.000Z","created_at":"2021-11-10T07:45:58.000Z","updated_at":"2021-11-10T07:45:58.000Z"},{"id":6961,"topicName":"Machining processes","topicDescription":null,"topicUniqueName":null,"chapter":600,"published_at":"2021-11-10T07:45:58.000Z","created_at":"2021-11-10T07:45:58.000Z","updated_at":"2021-11-10T07:45:58.000Z"},{"id":6962,"topicName":"Turning","topicDescription":null,"topicUniqueName":null,"chapter":600,"published_at":"2021-11-10T07:45:58.000Z","created_at":"2021-11-10T07:45:58.000Z","updated_at":"2021-11-10T07:45:58.000Z"},{"id":6963,"topicName":"Taper turning","topicDescription":null,"topicUniqueName":null,"chapter":600,"published_at":"2021-11-10T07:45:58.000Z","created_at":"2021-11-10T07:45:58.000Z","updated_at":"2021-11-10T07:45:58.000Z"},{"id":6964,"topicName":"Thread cutting","topicDescription":null,"topicUniqueName":null,"chapter":600,"published_at":"2021-11-10T07:45:58.000Z","created_at":"2021-11-10T07:45:58.000Z","updated_at":"2021-11-10T07:45:58.000Z"},{"id":6965,"topicName":"Drilling","topicDescription":null,"topicUniqueName":null,"chapter":600,"published_at":"2021-11-10T07:45:59.000Z","created_at":"2021-11-10T07:45:59.000Z","updated_at":"2021-11-10T07:45:59.000Z"},{"id":6966,"topicName":"Boring","topicDescription":null,"topicUniqueName":null,"chapter":600,"published_at":"2021-11-10T07:45:59.000Z","created_at":"2021-11-10T07:45:59.000Z","updated_at":"2021-11-10T07:45:59.000Z"},{"id":6967,"topicName":"Milling","topicDescription":null,"topicUniqueName":null,"chapter":600,"published_at":"2021-11-10T07:45:59.000Z","created_at":"2021-11-10T07:45:59.000Z","updated_at":"2021-11-10T07:45:59.000Z"},{"id":6968,"topicName":"Gear cutting","topicDescription":null,"topicUniqueName":null,"chapter":600,"published_at":"2021-11-10T07:45:59.000Z","created_at":"2021-11-10T07:45:59.000Z","updated_at":"2021-11-10T07:45:59.000Z"},{"id":6969,"topicName":"Thread production","topicDescription":null,"topicUniqueName":null,"chapter":600,"published_at":"2021-11-10T07:45:59.000Z","created_at":"2021-11-10T07:45:59.000Z","updated_at":"2021-11-10T07:45:59.000Z"},{"id":6970,"topicName":"Finishing processes","topicDescription":null,"topicUniqueName":null,"chapter":600,"published_at":"2021-11-10T07:45:59.000Z","created_at":"2021-11-10T07:45:59.000Z","updated_at":"2021-11-10T07:45:59.000Z"},{"id":6971,"topicName":"Grinding","topicDescription":null,"topicUniqueName":null,"chapter":600,"published_at":"2021-11-10T07:45:59.000Z","created_at":"2021-11-10T07:45:59.000Z","updated_at":"2021-11-10T07:46:00.000Z"},{"id":6972,"topicName":"Honing","topicDescription":null,"topicUniqueName":null,"chapter":600,"published_at":"2021-11-10T07:46:00.000Z","created_at":"2021-11-10T07:46:00.000Z","updated_at":"2021-11-10T07:46:00.000Z"},{"id":6973,"topicName":"Lapping","topicDescription":null,"topicUniqueName":null,"chapter":600,"published_at":"2021-11-10T07:46:00.000Z","created_at":"2021-11-10T07:46:00.000Z","updated_at":"2021-11-10T07:46:00.000Z"},{"id":6974,"topicName":"Super-finishing","topicDescription":null,"topicUniqueName":null,"chapter":600,"published_at":"2021-11-10T07:46:00.000Z","created_at":"2021-11-10T07:46:00.000Z","updated_at":"2021-11-10T07:46:01.000Z"},{"id":6975,"topicName":"Lathe machines","topicDescription":null,"topicUniqueName":null,"chapter":601,"published_at":"2021-11-10T07:48:37.000Z","created_at":"2021-11-10T07:48:37.000Z","updated_at":"2021-11-10T07:48:37.000Z"},{"id":6976,"topicName":"Milling machines","topicDescription":null,"topicUniqueName":null,"chapter":601,"published_at":"2021-11-10T07:48:37.000Z","created_at":"2021-11-10T07:48:37.000Z","updated_at":"2021-11-10T07:48:37.000Z"},{"id":6977,"topicName":"Drilling machines","topicDescription":null,"topicUniqueName":null,"chapter":601,"published_at":"2021-11-10T07:48:37.000Z","created_at":"2021-11-10T07:48:37.000Z","updated_at":"2021-11-10T07:48:37.000Z"},{"id":6978,"topicName":"Shaping machines","topicDescription":null,"topicUniqueName":null,"chapter":601,"published_at":"2021-11-10T07:48:38.000Z","created_at":"2021-11-10T07:48:38.000Z","updated_at":"2021-11-10T07:48:38.000Z"},{"id":6979,"topicName":"Machines construction and kinematics","topicDescription":null,"topicUniqueName":null,"chapter":601,"published_at":"2021-11-10T07:48:38.000Z","created_at":"2021-11-10T07:48:38.000Z","updated_at":"2021-11-10T07:48:38.000Z"},{"id":6980,"topicName":"Jigs and fixtures : principles/ applications and design","topicDescription":null,"topicUniqueName":null,"chapter":601,"published_at":"2021-11-10T07:48:38.000Z","created_at":"2021-11-10T07:48:38.000Z","updated_at":"2021-11-10T07:48:38.000Z"},{"id":6981,"topicName":"Principles and applications of USM","topicDescription":null,"topicUniqueName":null,"chapter":602,"published_at":"2021-11-10T07:50:27.000Z","created_at":"2021-11-10T07:50:27.000Z","updated_at":"2021-11-10T07:50:27.000Z"},{"id":6982,"topicName":" AJM","topicDescription":null,"topicUniqueName":null,"chapter":602,"published_at":"2021-11-10T07:50:27.000Z","created_at":"2021-11-10T07:50:27.000Z","updated_at":"2021-11-10T07:50:27.000Z"},{"id":6983,"topicName":" WJM","topicDescription":null,"topicUniqueName":null,"chapter":602,"published_at":"2021-11-10T07:50:28.000Z","created_at":"2021-11-10T07:50:28.000Z","updated_at":"2021-11-10T07:50:28.000Z"},{"id":6984,"topicName":" AWJM","topicDescription":null,"topicUniqueName":null,"chapter":602,"published_at":"2021-11-10T07:50:28.000Z","created_at":"2021-11-10T07:50:28.000Z","updated_at":"2021-11-10T07:50:28.000Z"},{"id":6985,"topicName":" EDM and Wire EDM","topicDescription":null,"topicUniqueName":null,"chapter":602,"published_at":"2021-11-10T07:50:28.000Z","created_at":"2021-11-10T07:50:28.000Z","updated_at":"2021-11-10T07:50:28.000Z"},{"id":6986,"topicName":" LBM","topicDescription":null,"topicUniqueName":null,"chapter":602,"published_at":"2021-11-10T07:50:28.000Z","created_at":"2021-11-10T07:50:28.000Z","updated_at":"2021-11-10T07:50:28.000Z"},{"id":6987,"topicName":" EBM","topicDescription":null,"topicUniqueName":null,"chapter":602,"published_at":"2021-11-10T07:50:28.000Z","created_at":"2021-11-10T07:50:28.000Z","updated_at":"2021-11-10T07:50:28.000Z"},{"id":6988,"topicName":" PAM","topicDescription":null,"topicUniqueName":null,"chapter":602,"published_at":"2021-11-10T07:50:28.000Z","created_at":"2021-11-10T07:50:28.000Z","updated_at":"2021-11-10T07:50:28.000Z"},{"id":6989,"topicName":" CHM","topicDescription":null,"topicUniqueName":null,"chapter":602,"published_at":"2021-11-10T07:50:29.000Z","created_at":"2021-11-10T07:50:29.000Z","updated_at":"2021-11-10T07:50:29.000Z"},{"id":6990,"topicName":" ECM","topicDescription":null,"topicUniqueName":null,"chapter":602,"published_at":"2021-11-10T07:50:29.000Z","created_at":"2021-11-10T07:50:29.000Z","updated_at":"2021-11-10T07:50:29.000Z"},{"id":6991,"topicName":"Effect of process parameters on material removal rate / surface roughness and power consumption","topicDescription":null,"topicUniqueName":null,"chapter":602,"published_at":"2021-11-10T07:50:29.000Z","created_at":"2021-11-10T07:50:29.000Z","updated_at":"2021-11-10T07:50:29.000Z"},{"id":6992,"topicName":"Additive manufacturing techniques","topicDescription":null,"topicUniqueName":null,"chapter":602,"published_at":"2021-11-10T07:50:29.000Z","created_at":"2021-11-10T07:50:29.000Z","updated_at":"2021-11-10T07:50:29.000Z"},{"id":6993,"topicName":"Basic concepts of CAD and CAM","topicDescription":null,"topicUniqueName":null,"chapter":603,"published_at":"2021-11-10T07:52:00.000Z","created_at":"2021-11-10T07:52:00.000Z","updated_at":"2021-11-10T07:52:00.000Z"},{"id":6994,"topicName":"Geometric modeling","topicDescription":null,"topicUniqueName":null,"chapter":603,"published_at":"2021-11-10T07:52:00.000Z","created_at":"2021-11-10T07:52:00.000Z","updated_at":"2021-11-10T07:52:01.000Z"},{"id":6995,"topicName":"CNC","topicDescription":null,"topicUniqueName":null,"chapter":603,"published_at":"2021-11-10T07:52:01.000Z","created_at":"2021-11-10T07:52:01.000Z","updated_at":"2021-11-10T07:52:01.000Z"},{"id":6996,"topicName":"Automation in Manufacturing","topicDescription":null,"topicUniqueName":null,"chapter":603,"published_at":"2021-11-10T07:52:01.000Z","created_at":"2021-11-10T07:52:01.000Z","updated_at":"2021-11-10T07:52:01.000Z"},{"id":6997,"topicName":"Industrial Robots : configurations/ drives and controls","topicDescription":null,"topicUniqueName":null,"chapter":603,"published_at":"2021-11-10T07:52:01.000Z","created_at":"2021-11-10T07:52:01.000Z","updated_at":"2021-11-10T07:52:01.000Z"},{"id":6998,"topicName":"Cellular manufacturing and FMS","topicDescription":null,"topicUniqueName":null,"chapter":603,"published_at":"2021-11-10T07:52:01.000Z","created_at":"2021-11-10T07:52:01.000Z","updated_at":"2021-11-10T07:52:01.000Z"},{"id":6999,"topicName":"Group Technology","topicDescription":null,"topicUniqueName":null,"chapter":603,"published_at":"2021-11-10T07:52:02.000Z","created_at":"2021-11-10T07:52:02.000Z","updated_at":"2021-11-10T07:52:02.000Z"},{"id":7000,"topicName":"CAPP","topicDescription":null,"topicUniqueName":null,"chapter":603,"published_at":"2021-11-10T07:52:02.000Z","created_at":"2021-11-10T07:52:02.000Z","updated_at":"2021-11-10T07:52:02.000Z"},{"id":7001,"topicName":"Accuracy and precision","topicDescription":null,"topicUniqueName":null,"chapter":604,"published_at":"2021-11-10T07:53:57.000Z","created_at":"2021-11-10T07:53:57.000Z","updated_at":"2021-11-10T07:53:57.000Z"},{"id":7002,"topicName":"Types of errors","topicDescription":null,"topicUniqueName":null,"chapter":604,"published_at":"2021-11-10T07:53:57.000Z","created_at":"2021-11-10T07:53:57.000Z","updated_at":"2021-11-10T07:53:57.000Z"},{"id":7003,"topicName":"Limits- fits and tolerances","topicDescription":null,"topicUniqueName":null,"chapter":604,"published_at":"2021-11-10T07:53:57.000Z","created_at":"2021-11-10T07:53:57.000Z","updated_at":"2021-11-10T07:53:57.000Z"},{"id":7004,"topicName":"Gauge design","topicDescription":null,"topicUniqueName":null,"chapter":604,"published_at":"2021-11-10T07:53:58.000Z","created_at":"2021-11-10T07:53:58.000Z","updated_at":"2021-11-10T07:53:58.000Z"},{"id":7005,"topicName":"Interchangeability","topicDescription":null,"topicUniqueName":null,"chapter":604,"published_at":"2021-11-10T07:53:58.000Z","created_at":"2021-11-10T07:53:58.000Z","updated_at":"2021-11-10T07:53:58.000Z"},{"id":7006,"topicName":"Selective assembly","topicDescription":null,"topicUniqueName":null,"chapter":604,"published_at":"2021-11-10T07:53:58.000Z","created_at":"2021-11-10T07:53:58.000Z","updated_at":"2021-11-10T07:53:58.000Z"},{"id":7007,"topicName":"Linear-angular and form measurements (straightness/ flatness/ roundness/ runout and cylindricity) by mechanical and optical methods","topicDescription":null,"topicUniqueName":null,"chapter":604,"published_at":"2021-11-10T07:53:58.000Z","created_at":"2021-11-10T07:53:58.000Z","updated_at":"2021-11-10T07:53:58.000Z"},{"id":7008,"topicName":"Inspection of screw threads and gears","topicDescription":null,"topicUniqueName":null,"chapter":604,"published_at":"2021-11-10T07:53:58.000Z","created_at":"2021-11-10T07:53:58.000Z","updated_at":"2021-11-10T07:53:58.000Z"},{"id":7009,"topicName":"Surface roughness measurement by contact and non-contact methods","topicDescription":null,"topicUniqueName":null,"chapter":604,"published_at":"2021-11-10T07:53:59.000Z","created_at":"2021-11-10T07:53:59.000Z","updated_at":"2021-11-10T07:53:59.000Z"},{"id":7010,"topicName":"Quality – Concept and costs","topicDescription":null,"topicUniqueName":null,"chapter":605,"published_at":"2021-11-10T07:55:30.000Z","created_at":"2021-11-10T07:55:30.000Z","updated_at":"2021-11-10T07:55:30.000Z"},{"id":7011,"topicName":"Statistical quality control","topicDescription":null,"topicUniqueName":null,"chapter":605,"published_at":"2021-11-10T07:55:30.000Z","created_at":"2021-11-10T07:55:30.000Z","updated_at":"2021-11-10T07:55:31.000Z"},{"id":7012,"topicName":"Process capability analysis","topicDescription":null,"topicUniqueName":null,"chapter":605,"published_at":"2021-11-10T07:55:31.000Z","created_at":"2021-11-10T07:55:31.000Z","updated_at":"2021-11-10T07:55:31.000Z"},{"id":7013,"topicName":"Control charts for variables and attributes and acceptance sampling","topicDescription":null,"topicUniqueName":null,"chapter":605,"published_at":"2021-11-10T07:55:31.000Z","created_at":"2021-11-10T07:55:31.000Z","updated_at":"2021-11-10T07:55:31.000Z"},{"id":7014,"topicName":"Six sigma","topicDescription":null,"topicUniqueName":null,"chapter":605,"published_at":"2021-11-10T07:55:31.000Z","created_at":"2021-11-10T07:55:31.000Z","updated_at":"2021-11-10T07:55:31.000Z"},{"id":7015,"topicName":"Total quality management","topicDescription":null,"topicUniqueName":null,"chapter":605,"published_at":"2021-11-10T07:55:31.000Z","created_at":"2021-11-10T07:55:31.000Z","updated_at":"2021-11-10T07:55:31.000Z"},{"id":7016,"topicName":"Quality assurance and certification","topicDescription":null,"topicUniqueName":null,"chapter":605,"published_at":"2021-11-10T07:55:31.000Z","created_at":"2021-11-10T07:55:31.000Z","updated_at":"2021-11-10T07:55:31.000Z"},{"id":7017,"topicName":"ISO 9000","topicDescription":null,"topicUniqueName":null,"chapter":605,"published_at":"2021-11-10T07:55:32.000Z","created_at":"2021-11-10T07:55:32.000Z","updated_at":"2021-11-10T07:55:32.000Z"},{"id":7018,"topicName":" ISO14000","topicDescription":null,"topicUniqueName":null,"chapter":605,"published_at":"2021-11-10T07:55:32.000Z","created_at":"2021-11-10T07:55:32.000Z","updated_at":"2021-11-10T07:55:32.000Z"},{"id":7019,"topicName":"Reliability","topicDescription":null,"topicUniqueName":null,"chapter":606,"published_at":"2021-11-10T07:57:19.000Z","created_at":"2021-11-10T07:57:19.000Z","updated_at":"2021-11-10T07:57:19.000Z"},{"id":7020,"topicName":"Availability","topicDescription":null,"topicUniqueName":null,"chapter":606,"published_at":"2021-11-10T07:57:20.000Z","created_at":"2021-11-10T07:57:20.000Z","updated_at":"2021-11-10T07:57:20.000Z"},{"id":7021,"topicName":"Maintainability","topicDescription":null,"topicUniqueName":null,"chapter":606,"published_at":"2021-11-10T07:57:20.000Z","created_at":"2021-11-10T07:57:20.000Z","updated_at":"2021-11-10T07:57:20.000Z"},{"id":7022,"topicName":"Distribution of failure and repair times","topicDescription":null,"topicUniqueName":null,"chapter":606,"published_at":"2021-11-10T07:57:20.000Z","created_at":"2021-11-10T07:57:20.000Z","updated_at":"2021-11-10T07:57:20.000Z"},{"id":7023,"topicName":"Determination of MTBF and MTTR","topicDescription":null,"topicUniqueName":null,"chapter":606,"published_at":"2021-11-10T07:57:20.000Z","created_at":"2021-11-10T07:57:20.000Z","updated_at":"2021-11-10T07:57:20.000Z"},{"id":7024,"topicName":"Reliability models","topicDescription":null,"topicUniqueName":null,"chapter":606,"published_at":"2021-11-10T07:57:20.000Z","created_at":"2021-11-10T07:57:20.000Z","updated_at":"2021-11-10T07:57:20.000Z"},{"id":7025,"topicName":"Determination of system reliability","topicDescription":null,"topicUniqueName":null,"chapter":606,"published_at":"2021-11-10T07:57:21.000Z","created_at":"2021-11-10T07:57:21.000Z","updated_at":"2021-11-10T07:57:21.000Z"},{"id":7026,"topicName":"Preventive and predictive maintenance and replacement","topicDescription":null,"topicUniqueName":null,"chapter":606,"published_at":"2021-11-10T07:57:21.000Z","created_at":"2021-11-10T07:57:21.000Z","updated_at":"2021-11-10T07:57:21.000Z"},{"id":7027,"topicName":"Total productive maintenance","topicDescription":null,"topicUniqueName":null,"chapter":606,"published_at":"2021-11-10T07:57:21.000Z","created_at":"2021-11-10T07:57:21.000Z","updated_at":"2021-11-10T07:57:21.000Z"},{"id":7028,"topicName":"Principles of product design","topicDescription":null,"topicUniqueName":null,"chapter":607,"published_at":"2021-11-10T07:59:26.000Z","created_at":"2021-11-10T07:59:26.000Z","updated_at":"2021-11-10T07:59:26.000Z"},{"id":7029,"topicName":"Tolerance design","topicDescription":null,"topicUniqueName":null,"chapter":607,"published_at":"2021-11-10T07:59:26.000Z","created_at":"2021-11-10T07:59:26.000Z","updated_at":"2021-11-10T07:59:26.000Z"},{"id":7030,"topicName":"Quality and cost considerations","topicDescription":null,"topicUniqueName":null,"chapter":607,"published_at":"2021-11-10T07:59:26.000Z","created_at":"2021-11-10T07:59:26.000Z","updated_at":"2021-11-10T07:59:26.000Z"},{"id":7031,"topicName":"Product life cycle","topicDescription":null,"topicUniqueName":null,"chapter":607,"published_at":"2021-11-10T07:59:26.000Z","created_at":"2021-11-10T07:59:26.000Z","updated_at":"2021-11-10T07:59:26.000Z"},{"id":7032,"topicName":"Standardization","topicDescription":null,"topicUniqueName":null,"chapter":607,"published_at":"2021-11-10T07:59:27.000Z","created_at":"2021-11-10T07:59:27.000Z","updated_at":"2021-11-10T07:59:27.000Z"},{"id":7033,"topicName":"Simplification","topicDescription":null,"topicUniqueName":null,"chapter":607,"published_at":"2021-11-10T07:59:27.000Z","created_at":"2021-11-10T07:59:27.000Z","updated_at":"2021-11-10T07:59:27.000Z"},{"id":7034,"topicName":"Diversification","topicDescription":null,"topicUniqueName":null,"chapter":607,"published_at":"2021-11-10T07:59:27.000Z","created_at":"2021-11-10T07:59:27.000Z","updated_at":"2021-11-10T07:59:27.000Z"},{"id":7035,"topicName":"Value engineering and analysis","topicDescription":null,"topicUniqueName":null,"chapter":607,"published_at":"2021-11-10T07:59:27.000Z","created_at":"2021-11-10T07:59:27.000Z","updated_at":"2021-11-10T07:59:27.000Z"},{"id":7036,"topicName":"Concurrent engineering","topicDescription":null,"topicUniqueName":null,"chapter":607,"published_at":"2021-11-10T07:59:27.000Z","created_at":"2021-11-10T07:59:27.000Z","updated_at":"2021-11-10T07:59:27.000Z"},{"id":7037,"topicName":"Design for “X\"","topicDescription":null,"topicUniqueName":null,"chapter":607,"published_at":"2021-11-10T07:59:27.000Z","created_at":"2021-11-10T07:59:27.000Z","updated_at":"2021-11-10T07:59:28.000Z"},{"id":7038,"topicName":"Taylor’s scientific management","topicDescription":null,"topicUniqueName":null,"chapter":608,"published_at":"2021-11-10T08:01:05.000Z","created_at":"2021-11-10T08:01:05.000Z","updated_at":"2021-11-10T08:01:05.000Z"},{"id":7039,"topicName":"Gilbreths’s contributions","topicDescription":null,"topicUniqueName":null,"chapter":608,"published_at":"2021-11-10T08:01:06.000Z","created_at":"2021-11-10T08:01:06.000Z","updated_at":"2021-11-10T08:01:06.000Z"},{"id":7040,"topicName":"Productivity – concepts and measurements","topicDescription":null,"topicUniqueName":null,"chapter":608,"published_at":"2021-11-10T08:01:06.000Z","created_at":"2021-11-10T08:01:06.000Z","updated_at":"2021-11-10T08:01:06.000Z"},{"id":7041,"topicName":"Method study","topicDescription":null,"topicUniqueName":null,"chapter":608,"published_at":"2021-11-10T08:01:06.000Z","created_at":"2021-11-10T08:01:06.000Z","updated_at":"2021-11-10T08:01:06.000Z"},{"id":7042,"topicName":"Micro-motion study","topicDescription":null,"topicUniqueName":null,"chapter":608,"published_at":"2021-11-10T08:01:06.000Z","created_at":"2021-11-10T08:01:06.000Z","updated_at":"2021-11-10T08:01:06.000Z"},{"id":7043,"topicName":"Principles of motion economy","topicDescription":null,"topicUniqueName":null,"chapter":608,"published_at":"2021-11-10T08:01:06.000Z","created_at":"2021-11-10T08:01:06.000Z","updated_at":"2021-11-10T08:01:06.000Z"},{"id":7044,"topicName":"Work measurement","topicDescription":null,"topicUniqueName":null,"chapter":608,"published_at":"2021-11-10T08:01:06.000Z","created_at":"2021-11-10T08:01:06.000Z","updated_at":"2021-11-10T08:01:06.000Z"},{"id":7045,"topicName":"Time study","topicDescription":null,"topicUniqueName":null,"chapter":608,"published_at":"2021-11-10T08:01:07.000Z","created_at":"2021-11-10T08:01:07.000Z","updated_at":"2021-11-10T08:01:07.000Z"},{"id":7046,"topicName":"Work sampling","topicDescription":null,"topicUniqueName":null,"chapter":608,"published_at":"2021-11-10T08:01:07.000Z","created_at":"2021-11-10T08:01:07.000Z","updated_at":"2021-11-10T08:01:07.000Z"},{"id":7047,"topicName":"Standard data","topicDescription":null,"topicUniqueName":null,"chapter":608,"published_at":"2021-11-10T08:01:07.000Z","created_at":"2021-11-10T08:01:07.000Z","updated_at":"2021-11-10T08:01:07.000Z"},{"id":7048,"topicName":"PMTS","topicDescription":null,"topicUniqueName":null,"chapter":608,"published_at":"2021-11-10T08:01:07.000Z","created_at":"2021-11-10T08:01:07.000Z","updated_at":"2021-11-10T08:01:07.000Z"},{"id":7049,"topicName":"Ergonomics","topicDescription":null,"topicUniqueName":null,"chapter":608,"published_at":"2021-11-10T08:01:07.000Z","created_at":"2021-11-10T08:01:07.000Z","updated_at":"2021-11-10T08:01:07.000Z"},{"id":7050,"topicName":"Job evaluation and merit rating","topicDescription":null,"topicUniqueName":null,"chapter":608,"published_at":"2021-11-10T08:01:08.000Z","created_at":"2021-11-10T08:01:08.000Z","updated_at":"2021-11-10T08:01:08.000Z"},{"id":7051,"topicName":"Facility location factors and evaluation of alternate locations","topicDescription":null,"topicUniqueName":null,"chapter":609,"published_at":"2021-11-10T08:02:14.000Z","created_at":"2021-11-10T08:02:14.000Z","updated_at":"2021-11-10T08:02:14.000Z"},{"id":7052,"topicName":"Types of plant layout and their evaluation","topicDescription":null,"topicUniqueName":null,"chapter":609,"published_at":"2021-11-10T08:02:14.000Z","created_at":"2021-11-10T08:02:14.000Z","updated_at":"2021-11-10T08:02:14.000Z"},{"id":7053,"topicName":"Computer aided layout design techniques","topicDescription":null,"topicUniqueName":null,"chapter":609,"published_at":"2021-11-10T08:02:14.000Z","created_at":"2021-11-10T08:02:14.000Z","updated_at":"2021-11-10T08:02:14.000Z"},{"id":7054,"topicName":"Assembly line balancing","topicDescription":null,"topicUniqueName":null,"chapter":609,"published_at":"2021-11-10T08:02:15.000Z","created_at":"2021-11-10T08:02:15.000Z","updated_at":"2021-11-10T08:02:15.000Z"},{"id":7055,"topicName":"Materials handling systems","topicDescription":null,"topicUniqueName":null,"chapter":609,"published_at":"2021-11-10T08:02:15.000Z","created_at":"2021-11-10T08:02:15.000Z","updated_at":"2021-11-10T08:02:15.000Z"},{"id":7056,"topicName":"Linear programming","topicDescription":null,"topicUniqueName":null,"chapter":610,"published_at":"2021-11-10T08:03:47.000Z","created_at":"2021-11-10T08:03:47.000Z","updated_at":"2021-11-10T08:03:47.000Z"},{"id":7057,"topicName":"Problem formulation","topicDescription":null,"topicUniqueName":null,"chapter":610,"published_at":"2021-11-10T08:03:47.000Z","created_at":"2021-11-10T08:03:47.000Z","updated_at":"2021-11-10T08:03:47.000Z"},{"id":7058,"topicName":"Simplex method","topicDescription":null,"topicUniqueName":null,"chapter":610,"published_at":"2021-11-10T08:03:47.000Z","created_at":"2021-11-10T08:03:47.000Z","updated_at":"2021-11-10T08:03:47.000Z"},{"id":7059,"topicName":"Duality and sensitivity analysis","topicDescription":null,"topicUniqueName":null,"chapter":610,"published_at":"2021-11-10T08:03:48.000Z","created_at":"2021-11-10T08:03:48.000Z","updated_at":"2021-11-10T08:03:48.000Z"},{"id":7060,"topicName":"Transportation and assignment models","topicDescription":null,"topicUniqueName":null,"chapter":610,"published_at":"2021-11-10T08:03:48.000Z","created_at":"2021-11-10T08:03:48.000Z","updated_at":"2021-11-10T08:03:48.000Z"},{"id":7061,"topicName":"Integer programming","topicDescription":null,"topicUniqueName":null,"chapter":610,"published_at":"2021-11-10T08:03:48.000Z","created_at":"2021-11-10T08:03:48.000Z","updated_at":"2021-11-10T08:03:48.000Z"},{"id":7062,"topicName":"Constrained and unconstrained nonlinear optimization","topicDescription":null,"topicUniqueName":null,"chapter":610,"published_at":"2021-11-10T08:03:48.000Z","created_at":"2021-11-10T08:03:48.000Z","updated_at":"2021-11-10T08:03:48.000Z"},{"id":7063,"topicName":"Markovian queuing models","topicDescription":null,"topicUniqueName":null,"chapter":610,"published_at":"2021-11-10T08:03:48.000Z","created_at":"2021-11-10T08:03:48.000Z","updated_at":"2021-11-10T08:03:48.000Z"},{"id":7064,"topicName":"Simulation – manufacturing applications","topicDescription":null,"topicUniqueName":null,"chapter":610,"published_at":"2021-11-10T08:03:49.000Z","created_at":"2021-11-10T08:03:49.000Z","updated_at":"2021-11-10T08:03:49.000Z"},{"id":7065,"topicName":"Elementary cost accounting and methods of depreciation","topicDescription":null,"topicUniqueName":null,"chapter":611,"published_at":"2021-11-10T08:04:53.000Z","created_at":"2021-11-10T08:04:53.000Z","updated_at":"2021-11-10T08:04:53.000Z"},{"id":7066,"topicName":"Break-even analysis","topicDescription":null,"topicUniqueName":null,"chapter":611,"published_at":"2021-11-10T08:04:53.000Z","created_at":"2021-11-10T08:04:53.000Z","updated_at":"2021-11-10T08:04:53.000Z"},{"id":7067,"topicName":"Techniques for evaluation of capital investments","topicDescription":null,"topicUniqueName":null,"chapter":611,"published_at":"2021-11-10T08:04:53.000Z","created_at":"2021-11-10T08:04:53.000Z","updated_at":"2021-11-10T08:04:53.000Z"},{"id":7068,"topicName":"Financial statements","topicDescription":null,"topicUniqueName":null,"chapter":611,"published_at":"2021-11-10T08:04:53.000Z","created_at":"2021-11-10T08:04:53.000Z","updated_at":"2021-11-10T08:04:53.000Z"},{"id":7069,"topicName":"Activity based costing","topicDescription":null,"topicUniqueName":null,"chapter":611,"published_at":"2021-11-10T08:04:53.000Z","created_at":"2021-11-10T08:04:53.000Z","updated_at":"2021-11-10T08:04:53.000Z"},{"id":7070,"topicName":"Forecasting techniques","topicDescription":null,"topicUniqueName":null,"chapter":612,"published_at":"2021-11-10T13:15:05.000Z","created_at":"2021-11-10T13:15:05.000Z","updated_at":"2021-11-10T13:15:05.000Z"},{"id":7071,"topicName":"Causal and time series models","topicDescription":null,"topicUniqueName":null,"chapter":612,"published_at":"2021-11-10T13:15:05.000Z","created_at":"2021-11-10T13:15:05.000Z","updated_at":"2021-11-10T13:15:05.000Z"},{"id":7072,"topicName":"Moving average","topicDescription":null,"topicUniqueName":null,"chapter":612,"published_at":"2021-11-10T13:15:05.000Z","created_at":"2021-11-10T13:15:05.000Z","updated_at":"2021-11-10T13:15:05.000Z"},{"id":7073,"topicName":"Exponential smoothing","topicDescription":null,"topicUniqueName":null,"chapter":612,"published_at":"2021-11-10T13:15:05.000Z","created_at":"2021-11-10T13:15:05.000Z","updated_at":"2021-11-10T13:15:05.000Z"},{"id":7074,"topicName":"Trend and seasonality","topicDescription":null,"topicUniqueName":null,"chapter":612,"published_at":"2021-11-10T13:15:06.000Z","created_at":"2021-11-10T13:15:06.000Z","updated_at":"2021-11-10T13:15:06.000Z"},{"id":7075,"topicName":"Aggregate production planning","topicDescription":null,"topicUniqueName":null,"chapter":612,"published_at":"2021-11-10T13:15:06.000Z","created_at":"2021-11-10T13:15:06.000Z","updated_at":"2021-11-10T13:15:06.000Z"},{"id":7076,"topicName":"Master production scheduling","topicDescription":null,"topicUniqueName":null,"chapter":612,"published_at":"2021-11-10T13:15:06.000Z","created_at":"2021-11-10T13:15:06.000Z","updated_at":"2021-11-10T13:15:06.000Z"},{"id":7077,"topicName":"MRP","topicDescription":null,"topicUniqueName":null,"chapter":612,"published_at":"2021-11-10T13:15:07.000Z","created_at":"2021-11-10T13:15:07.000Z","updated_at":"2021-11-10T13:15:07.000Z"},{"id":7078,"topicName":"MRP-II","topicDescription":null,"topicUniqueName":null,"chapter":612,"published_at":"2021-11-10T13:15:07.000Z","created_at":"2021-11-10T13:15:07.000Z","updated_at":"2021-11-10T13:15:07.000Z"},{"id":7079,"topicName":"ERP","topicDescription":null,"topicUniqueName":null,"chapter":612,"published_at":"2021-11-10T13:15:07.000Z","created_at":"2021-11-10T13:15:07.000Z","updated_at":"2021-11-10T13:15:07.000Z"},{"id":7080,"topicName":"Routing","topicDescription":null,"topicUniqueName":null,"chapter":612,"published_at":"2021-11-10T13:15:07.000Z","created_at":"2021-11-10T13:15:07.000Z","updated_at":"2021-11-10T13:15:07.000Z"},{"id":7081,"topicName":"Scheduling and priority dispatching","topicDescription":null,"topicUniqueName":null,"chapter":612,"published_at":"2021-11-10T13:15:07.000Z","created_at":"2021-11-10T13:15:07.000Z","updated_at":"2021-11-10T13:15:07.000Z"},{"id":7082,"topicName":"Push and pull production systems","topicDescription":null,"topicUniqueName":null,"chapter":612,"published_at":"2021-11-10T13:15:07.000Z","created_at":"2021-11-10T13:15:07.000Z","updated_at":"2021-11-10T13:15:08.000Z"},{"id":7083,"topicName":"Concepts of Lean and JIT manufacturing systems","topicDescription":null,"topicUniqueName":null,"chapter":612,"published_at":"2021-11-10T13:15:08.000Z","created_at":"2021-11-10T13:15:08.000Z","updated_at":"2021-11-10T13:15:08.000Z"},{"id":7084,"topicName":"Logistics","topicDescription":null,"topicUniqueName":null,"chapter":612,"published_at":"2021-11-10T13:15:08.000Z","created_at":"2021-11-10T13:15:08.000Z","updated_at":"2021-11-10T13:15:08.000Z"},{"id":7085,"topicName":"Distribution and supply chain management","topicDescription":null,"topicUniqueName":null,"chapter":612,"published_at":"2021-11-10T13:15:08.000Z","created_at":"2021-11-10T13:15:08.000Z","updated_at":"2021-11-10T13:15:08.000Z"},{"id":7086,"topicName":"Inventory – functions/ costs/ classifications","topicDescription":null,"topicUniqueName":null,"chapter":612,"published_at":"2021-11-10T13:15:08.000Z","created_at":"2021-11-10T13:15:08.000Z","updated_at":"2021-11-10T13:15:08.000Z"},{"id":7087,"topicName":"Deterministic inventory models","topicDescription":null,"topicUniqueName":null,"chapter":612,"published_at":"2021-11-10T13:15:08.000Z","created_at":"2021-11-10T13:15:08.000Z","updated_at":"2021-11-10T13:15:08.000Z"},{"id":7088,"topicName":"Quantity discount","topicDescription":null,"topicUniqueName":null,"chapter":612,"published_at":"2021-11-10T13:15:09.000Z","created_at":"2021-11-10T13:15:09.000Z","updated_at":"2021-11-10T13:15:09.000Z"},{"id":7089,"topicName":"Perpetual and periodic inventory control systems","topicDescription":null,"topicUniqueName":null,"chapter":612,"published_at":"2021-11-10T13:15:09.000Z","created_at":"2021-11-10T13:15:09.000Z","updated_at":"2021-11-10T13:15:09.000Z"},{"id":7090,"topicName":"Scheduling techniques","topicDescription":null,"topicUniqueName":null,"chapter":613,"published_at":"2021-11-10T13:17:23.000Z","created_at":"2021-11-10T13:17:23.000Z","updated_at":"2021-11-10T13:17:23.000Z"},{"id":7091,"topicName":"Gantt chart","topicDescription":null,"topicUniqueName":null,"chapter":613,"published_at":"2021-11-10T13:17:23.000Z","created_at":"2021-11-10T13:17:23.000Z","updated_at":"2021-11-10T13:17:23.000Z"},{"id":7092,"topicName":"CPM","topicDescription":null,"topicUniqueName":null,"chapter":613,"published_at":"2021-11-10T13:17:23.000Z","created_at":"2021-11-10T13:17:23.000Z","updated_at":"2021-11-10T13:17:23.000Z"},{"id":7093,"topicName":"PERT","topicDescription":null,"topicUniqueName":null,"chapter":613,"published_at":"2021-11-10T13:17:24.000Z","created_at":"2021-11-10T13:17:24.000Z","updated_at":"2021-11-10T13:17:24.000Z"},{"id":7094,"topicName":"GERT","topicDescription":null,"topicUniqueName":null,"chapter":613,"published_at":"2021-11-10T13:17:24.000Z","created_at":"2021-11-10T13:17:24.000Z","updated_at":"2021-11-10T13:17:24.000Z"}],"marks":[{"id":130,"marks":12,"chapter":null,"subject":13,"published_at":"2021-11-10T06:02:45.000Z","created_at":"2021-11-10T06:02:42.000Z","updated_at":"2021-11-11T14:43:39.000Z","phase":35},{"id":131,"marks":23,"chapter":null,"subject":98,"published_at":"2021-11-10T06:04:28.000Z","created_at":"2021-11-10T06:04:26.000Z","updated_at":"2021-11-11T14:43:39.000Z","phase":35},{"id":132,"marks":10,"chapter":null,"subject":99,"published_at":"2021-11-10T06:05:57.000Z","created_at":"2021-11-10T06:05:55.000Z","updated_at":"2021-11-11T14:43:39.000Z","phase":35},{"id":133,"marks":12,"chapter":null,"subject":100,"published_at":"2021-11-10T06:06:55.000Z","created_at":"2021-11-10T06:06:52.000Z","updated_at":"2021-11-11T14:43:39.000Z","phase":35},{"id":134,"marks":10,"chapter":null,"subject":101,"published_at":"2021-11-10T06:08:04.000Z","created_at":"2021-11-10T06:08:01.000Z","updated_at":"2021-11-11T14:43:39.000Z","phase":35},{"id":135,"marks":7,"chapter":null,"subject":102,"published_at":"2021-11-10T06:08:57.000Z","created_at":"2021-11-10T06:08:55.000Z","updated_at":"2021-11-11T14:43:39.000Z","phase":35},{"id":136,"marks":11,"chapter":null,"subject":103,"published_at":"2021-11-10T06:09:55.000Z","created_at":"2021-11-10T06:09:53.000Z","updated_at":"2021-11-11T14:43:39.000Z","phase":35},{"id":137,"marks":15,"chapter":null,"subject":17,"published_at":"2021-11-10T06:11:09.000Z","created_at":"2021-11-10T06:11:03.000Z","updated_at":"2021-11-11T14:43:39.000Z","phase":35}]}]
